<?xml version="1.0" encoding="UTF-8"?>
<torneo>
  <partido>
	<fecha>1 AGO</fecha>
	<hora>19:00</hora>
	<categoria>AFI</categoria>
	<grupo>I</grupo>
	<fase>LIGA</fase>
	<equipo>
	  <nombre>Ruano Rodrigo</nombre>
	  <set number="1">13</set>
	  <set number="2">7</set>
	  <set number="3">0</set>
	</equipo>
	<equipo>
	  <nombre>Rojas Casas</nombre>
	  <set number="1">15</set>
	  <set number="2">15</set>
	  <set number="3">0</set>
	</equipo>
  </partido>
  <partido>
	<fecha>1 AGO</fecha>
	<hora>19:30</hora>
	<categoria>AFI</categoria>
	<grupo>I</grupo>
	<fase>LIGA</fase>
	<equipo>
	  <nombre>All Stars</nombre>
	  <set number="1">15</set>
	  <set number="2">150</set>
	  <set number="3">0</set>
	</equipo>
	<equipo>
	  <nombre>Los Desastres Del Día 3</nombre>
	  <set number="1">5</set>
	  <set number="2">7</set>
	  <set number="3">0</set>
	</equipo>
  </partido>
  <partido>
	<fecha>1 AGO</fecha>
	<hora>20:00</hora>
	<categoria>AFI</categoria>
	<grupo>A</grupo>
	<fase>LIGA</fase>
	<equipo>
	  <nombre>Illescas Punzón</nombre>
	  <set number="1">15</set>
	  <set number="2">13</set>
	  <set number="3">11</set>
	</equipo>
	<equipo>
	  <nombre>Hermanos Martín</nombre>
	  <set number="1">12</set>
	  <set number="2">15</set>
	  <set number="3">5</set>
	</equipo>
  </partido>
  <partido>
	<fecha>1 AGO</fecha>
	<hora>19:00</hora>
	<categoria>AFM</categoria>
	<grupo>B</grupo>
	<fase>LIGA</fase>
	<equipo>
	  <nombre>Illescas Gallego</nombre>
	  <set number="1">15</set>
	  <set number="2">15</set>
	  <set number="3">0</set>
	</equipo>
	<equipo>
	  <nombre>El Punto Y La I</nombre>
	  <set number="1">12</set>
	  <set number="2">10</set>
	  <set number="3">0</set>
	</equipo>
  </partido>
  <partido>
	<fecha>1 AGO</fecha>
	<hora>19:30</hora>
	<categoria>AFI</categoria>
	<grupo>E</grupo>
	<fase>LIGA</fase>
	<equipo>
	  <nombre>Los Dalton</nombre>
	  <set number="1">15</set>
	  <set number="2">8</set>
	  <set number="3">15</set>
	</equipo>
	<equipo>
	  <nombre>Álvaro Y Carlos</nombre>
	  <set number="1">12</set>
	  <set number="2">15</set>
	  <set number="3">12</set>
	</equipo>
  </partido>
  <partido>
	<fecha>1 AGO</fecha>
	<hora>20:00</hora>
	<categoria>AFM</categoria>
	<grupo>A</grupo>
	<fase>LIGA</fase>
	<equipo>
	  <nombre>Milka Power</nombre>
	  <set number="1">1</set>
	  <set number="2">6</set>
	  <set number="3">0</set>
	</equipo>
	<equipo>
	  <nombre>Colacao Con Leche</nombre>
	  <set number="1">15</set>
	  <set number="2">15</set>
	  <set number="3">0</set>
	</equipo>
  </partido>
  <partido>
	<fecha>1 AGO</fecha>
	<hora>20:30</hora>
	<categoria>AFM</categoria>
	<grupo>B</grupo>
	<fase>LIGA</fase>
	<equipo>
	  <nombre>El Punto Y La I</nombre>
	  <set number="1">4</set>
	  <set number="2">11</set>
	  <set number="3">0</set>
	</equipo>
	<equipo>
	  <nombre>Álvaro Y Noe</nombre>
	  <set number="1">15</set>
	  <set number="2">15</set>
	  <set number="3">0</set>
	</equipo>
  </partido>
  <partido>
	<fecha>1 AGO</fecha>
	<hora>21:00</hora>
	<categoria>AFM</categoria>
	<grupo>A</grupo>
	<fase>LIGA</fase>
	<equipo>
	  <nombre>Rodrigo Rodrigo</nombre>
	  <set number="1">15</set>
	  <set number="2">15</set>
	  <set number="3">0</set>
	</equipo>
	<equipo>
	  <nombre>Milka Power</nombre>
	  <set number="1">13</set>
	  <set number="2">13</set>
	  <set number="3">0</set>
	</equipo>
  </partido>
  <partido>
	<fecha>1 AGO</fecha>
	<hora>20:30</hora>
	<categoria>AFI</categoria>
	<grupo>B</grupo>
	<fase>LIGA</fase>
	<equipo>
	  <nombre>Rastrerismos</nombre>
	  <set number="1">3</set>
	  <set number="2">10</set>
	  <set number="3">0</set>
	</equipo>
	<equipo>
	  <nombre>Los Del Rodeo</nombre>
	  <set number="1">15</set>
	  <set number="2">15</set>
	  <set number="3">0</set>
	</equipo>
  </partido>
  <partido>
	<fecha>1 AGO</fecha>
	<hora>21:30</hora>
	<categoria>AFM</categoria>
	<grupo>B</grupo>
	<fase>LIGA</fase>
	<equipo>
	  <nombre>Churricarri</nombre>
	  <set number="1">15</set>
	  <set number="2">15</set>
	  <set number="3">0</set>
	</equipo>
	<equipo>
	  <nombre>El Punto Y La I</nombre>
	  <set number="1">10</set>
	  <set number="2">7</set>
	  <set number="3">0</set>
	</equipo>
  </partido>
  <partido>
	<fecha>1 AGO</fecha>
	<hora>21:30</hora>
	<categoria>AFI</categoria>
	<grupo>I</grupo>
	<fase>LIGA</fase>
	<equipo>
	  <nombre>Ruano Rodrigo</nombre>
	  <set number="1">15</set>
	  <set number="2">15</set>
	  <set number="3">0</set>
	</equipo>
	<equipo>
	  <nombre>Los Desastres Del Día 3</nombre>
	  <set number="1">5</set>
	  <set number="2">10</set>
	  <set number="3">0</set>
	</equipo>
  </partido>
  <partido>
	<fecha>1 AGO</fecha>
	<hora>22:00</hora>
	<categoria>AFI</categoria>
	<grupo>B</grupo>
	<fase>LIGA</fase>
	<equipo>
	  <nombre>Rastrerismos</nombre>
	  <set number="1">15</set>
	  <set number="2">15</set>
	  <set number="3">0</set>
	</equipo>
	<equipo>
	  <nombre>Chinato Y Enrique</nombre>
	  <set number="1">11</set>
	  <set number="2">10</set>
	  <set number="3">0</set>
	</equipo>
  </partido>
  <partido>
	<fecha>1 AGO</fecha>
	<hora>22:30</hora>
	<categoria>AFI</categoria>
	<grupo>B</grupo>
	<fase>LIGA</fase>
	<equipo>
	  <nombre>El Rolón Volador</nombre>
	  <set number="1">15</set>
	  <set number="2">15</set>
	  <set number="3">0</set>
	</equipo>
	<equipo>
	  <nombre>Los Del Rodeo</nombre>
	  <set number="1">11</set>
	  <set number="2">11</set>
	  <set number="3">0</set>
	</equipo>
  </partido>
  <partido>
	<fecha>1 AGO</fecha>
	<hora>23:00</hora>
	<categoria>AFI</categoria>
	<grupo>D</grupo>
	<fase>LIGA</fase>
	<equipo>
	  <nombre>Albertonuels</nombre>
	  <set number="1">15</set>
	  <set number="2">15</set>
	  <set number="3">0</set>
	</equipo>
	<equipo>
	  <nombre>Viejas Glorias</nombre>
	  <set number="1">11</set>
	  <set number="2">12</set>
	  <set number="3">0</set>
	</equipo>
  </partido>
  <partido>
	<fecha>1 AGO</fecha>
	<hora>22:30</hora>
	<categoria>AFM</categoria>
	<grupo>B</grupo>
	<fase>LIGA</fase>
	<equipo>
	  <nombre>Álvaro Y Noe</nombre>
	  <set number="1">16</set>
	  <set number="2">15</set>
	  <set number="3">0</set>
	</equipo>
	<equipo>
	  <nombre>Churricarri</nombre>
	  <set number="1">14</set>
	  <set number="2">7</set>
	  <set number="3">0</set>
	</equipo>
  </partido>
  <partido>
	<fecha>1 AGO</fecha>
	<hora>23:00</hora>
	<categoria>AFM</categoria>
	<grupo>A</grupo>
	<fase>LIGA</fase>
	<equipo>
	  <nombre>Rodrigo Rodrigo</nombre>
	  <set number="1">9</set>
	  <set number="2">8</set>
	  <set number="3">0</set>
	</equipo>
	<equipo>
	  <nombre>Candela Donate</nombre>
	  <set number="1">15</set>
	  <set number="2">15</set>
	  <set number="3">0</set>
	</equipo>
  </partido>
  <partido>
	<fecha>1 AGO</fecha>
	<hora>21:00</hora>
	<categoria>AFI</categoria>
	<grupo>K</grupo>
	<fase>LIGA</fase>
	<equipo>
	  <nombre>Alaska Y Vaquerizo</nombre>
	  <set number="1">1</set>
	  <set number="2">16</set>
	  <set number="3">9</set>
	</equipo>
	<equipo>
	  <nombre>Bastante Gómez</nombre>
	  <set number="1">15</set>
	  <set number="2">14</set>
	  <set number="3">11</set>
	</equipo>
  </partido>
  <partido>
	<fecha>1 AGO</fecha>
	<hora>23:30</hora>
	<categoria>AFI</categoria>
	<grupo>C</grupo>
	<fase>LIGA</fase>
	<equipo>
	  <nombre>Frente Polisario</nombre>
	  <set number="1">15</set>
	  <set number="2">15</set>
	  <set number="3">0</set>
	</equipo>
	<equipo>
	  <nombre>Alioli</nombre>
	  <set number="1">10</set>
	  <set number="2">13</set>
	  <set number="3">0</set>
	</equipo>
  </partido>
  <partido>
	<fecha>1 AGO</fecha>
	<hora>00:00</hora>
	<categoria>AFI</categoria>
	<grupo>B</grupo>
	<fase>LIGA</fase>
	<equipo>
	  <nombre>El Rolón Volador</nombre>
	  <set number="1">15</set>
	  <set number="2">15</set>
	  <set number="3">0</set>
	</equipo>
	<equipo>
	  <nombre>Chinato Y Enrique</nombre>
	  <set number="1">8</set>
	  <set number="2">7</set>
	  <set number="3">0</set>
	</equipo>
  </partido>
  <partido>
	<fecha>1 AGO</fecha>
	<hora>00:30</hora>
	<categoria>AFI</categoria>
	<grupo>D</grupo>
	<fase>LIGA</fase>
	<equipo>
	  <nombre>Jumping Crew</nombre>
	  <set number="1">9</set>
	  <set number="2">13</set>
	  <set number="3">0</set>
	</equipo>
	<equipo>
	  <nombre>Albertonuels</nombre>
	  <set number="1">15</set>
	  <set number="2">15</set>
	  <set number="3">0</set>
	</equipo>
  </partido>
  <partido>
	<fecha>1 AGO</fecha>
	<hora>01:00</hora>
	<categoria>AFI</categoria>
	<grupo>C</grupo>
	<fase>LIGA</fase>
	<equipo>
	  <nombre>Frente Polisario</nombre>
	  <set number="1">15</set>
	  <set number="2">15</set>
	  <set number="3">0</set>
	</equipo>
	<equipo>
	  <nombre>Masturbaladilla</nombre>
	  <set number="1">6</set>
	  <set number="2">4</set>
	  <set number="3">0</set>
	</equipo>
  </partido>
  <partido>
	<fecha>1 AGO</fecha>
	<hora>01:30</hora>
	<categoria>AFI</categoria>
	<grupo>A</grupo>
	<fase>LIGA</fase>
	<equipo>
	  <nombre>Hermanos Martín</nombre>
	  <set number="1">15</set>
	  <set number="2">16</set>
	  <set number="3">0</set>
	</equipo>
	<equipo>
	  <nombre>Candela Rodrigo</nombre>
	  <set number="1">11</set>
	  <set number="2">14</set>
	  <set number="3">0</set>
	</equipo>
  </partido>
  <partido>
	<fecha>1 AGO</fecha>
	<hora>01:30</hora>
	<categoria>AFI</categoria>
	<grupo>F</grupo>
	<fase>LIGA</fase>
	<equipo>
	  <nombre>Andrés Y Sergio</nombre>
	  <set number="1">10</set>
	  <set number="2">7</set>
	  <set number="3">0</set>
	</equipo>
	<equipo>
	  <nombre>Rafa Y Óscar</nombre>
	  <set number="1">15</set>
	  <set number="2">15</set>
	  <set number="3">0</set>
	</equipo>
  </partido>
  <partido>
	<fecha>1 AGO</fecha>
	<hora>00:30</hora>
	<categoria>AFI</categoria>
	<grupo>F</grupo>
	<fase>LIGA</fase>
	<equipo>
	  <nombre>Los Bilowos</nombre>
	  <set number="1">16</set>
	  <set number="2">9</set>
	  <set number="3">9</set>
	</equipo>
	<equipo>
	  <nombre>Gatuli Kulkin</nombre>
	  <set number="1">14</set>
	  <set number="2">15</set>
	  <set number="3">11</set>
	</equipo>
  </partido>
  <partido>
	<fecha>1 AGO</fecha>
	<hora>00:00</hora>
	<categoria>AFM</categoria>
	<grupo>A</grupo>
	<fase>LIGA</fase>
	<equipo>
	  <nombre>Candela Donate</nombre>
	  <set number="1">15</set>
	  <set number="2">15</set>
	  <set number="3">0</set>
	</equipo>
	<equipo>
	  <nombre>Milka Power</nombre>
	  <set number="1">12</set>
	  <set number="2">10</set>
	  <set number="3">0</set>
	</equipo>
  </partido>
  <partido>
	<fecha>1 AGO</fecha>
	<hora>01:00</hora>
	<categoria>AFI</categoria>
	<grupo>E</grupo>
	<fase>LIGA</fase>
	<equipo>
	  <nombre>Jaime Y Manu</nombre>
	  <set number="1">6</set>
	  <set number="2">6</set>
	  <set number="3">0</set>
	</equipo>
	<equipo>
	  <nombre>Álvaro Y Carlos</nombre>
	  <set number="1">15</set>
	  <set number="2">15</set>
	  <set number="3">0</set>
	</equipo>
  </partido>
  <partido>
	<fecha>1 AGO</fecha>
	<hora>23:30</hora>
	<categoria>AFI</categoria>
	<grupo>F</grupo>
	<fase>LIGA</fase>
	<equipo>
	  <nombre>Rafa Y Óscar</nombre>
	  <set number="1">15</set>
	  <set number="2">15</set>
	  <set number="3">0</set>
	</equipo>
	<equipo>
	  <nombre>Gatuli Kulkin</nombre>
	  <set number="1">3</set>
	  <set number="2">12</set>
	  <set number="3">0</set>
	</equipo>
  </partido>
  <partido>
	<fecha>2 AGO</fecha>
	<hora>00:00</hora>
	<categoria>AFI</categoria>
	<grupo>K</grupo>
	<fase>LIGA</fase>
	<equipo>
	  <nombre>Alaska Y Vaquerizo</nombre>
	  <set number="1">15</set>
	  <set number="2">14</set>
	  <set number="3">11</set>
	</equipo>
	<equipo>
	  <nombre>La Catapulta Infernal</nombre>
	  <set number="1">9</set>
	  <set number="2">16</set>
	  <set number="3">9</set>
	</equipo>
  </partido>
  <partido>
	<fecha>2 AGO</fecha>
	<hora>18:30</hora>
	<categoria>AFI</categoria>
	<grupo>H</grupo>
	<fase>LIGA</fase>
	<equipo>
	  <nombre>Vargas Me Mira</nombre>
	  <set number="1">12</set>
	  <set number="2">15</set>
	  <set number="3">1</set>
	</equipo>
	<equipo>
	  <nombre>Mandril Y Comadreja</nombre>
	  <set number="1">15</set>
	  <set number="2">11</set>
	  <set number="3">11</set>
	</equipo>
  </partido>
  <partido>
	<fecha>2 AGO</fecha>
	<hora>19:00</hora>
	<categoria>AFI</categoria>
	<grupo>H</grupo>
	<fase>LIGA</fase>
	<equipo>
	  <nombre>Hervás Rodrigo</nombre>
	  <set number="1">11</set>
	  <set number="2">15</set>
	  <set number="3">6</set>
	</equipo>
	<equipo>
	  <nombre>Antonio Y Ramón</nombre>
	  <set number="1">15</set>
	  <set number="2">11</set>
	  <set number="3">11</set>
	</equipo>
  </partido>
  <partido>
	<fecha>2 AGO</fecha>
	<hora>19:30</hora>
	<categoria>AFI</categoria>
	<grupo>J</grupo>
	<fase>LIGA</fase>
	<equipo>
	  <nombre>Los Finger</nombre>
	  <set number="1">12</set>
	  <set number="2">9</set>
	  <set number="3">0</set>
	</equipo>
	<equipo>
	  <nombre>Agapito Y Juanfri</nombre>
	  <set number="1">15</set>
	  <set number="2">15</set>
	  <set number="3">0</set>
	</equipo>
  </partido>
  <partido>
	<fecha>2 AGO</fecha>
	<hora>21:30</hora>
	<categoria>AFI</categoria>
	<grupo>K</grupo>
	<fase>LIGA</fase>
	<equipo>
	  <nombre>Bastante Gómez</nombre>
	  <set number="1">15</set>
	  <set number="2">15</set>
	  <set number="3">0</set>
	</equipo>
	<equipo>
	  <nombre>La Catapulta Infernal</nombre>
	  <set number="1">4</set>
	  <set number="2">10</set>
	  <set number="3">0</set>
	</equipo>
  </partido>
  <partido>
	<fecha>2 AGO</fecha>
	<hora>20:30</hora>
	<categoria>AFM</categoria>
	<grupo>A</grupo>
	<fase>LIGA</fase>
	<equipo>
	  <nombre>Candela Donate</nombre>
	  <set number="1">13</set>
	  <set number="2">9</set>
	  <set number="3">0</set>
	</equipo>
	<equipo>
	  <nombre>Colacao Con Leche</nombre>
	  <set number="1">15</set>
	  <set number="2">15</set>
	  <set number="3">0</set>
	</equipo>
  </partido>
  <partido>
	<fecha>2 AGO</fecha>
	<hora>21:00</hora>
	<categoria>AFI</categoria>
	<grupo>H</grupo>
	<fase>LIGA</fase>
	<equipo>
	  <nombre>Antonio Y Ramón</nombre>
	  <set number="1">13</set>
	  <set number="2">15</set>
	  <set number="3">7</set>
	</equipo>
	<equipo>
	  <nombre>Mandril Y Comadreja</nombre>
	  <set number="1">15</set>
	  <set number="2">12</set>
	  <set number="3">11</set>
	</equipo>
  </partido>
  <partido>
	<fecha>2 AGO</fecha>
	<hora>21:30</hora>
	<categoria>AFM</categoria>
	<grupo>A</grupo>
	<fase>LIGA</fase>
	<equipo>
	  <nombre>Alberto Y Ángela</nombre>
	  <set number="1">0</set>
	  <set number="2">0</set>
	  <set number="3">0</set>
	</equipo>
	<equipo>
	  <nombre>Milka Power</nombre>
	  <set number="1">15</set>
	  <set number="2">15</set>
	  <set number="3">0</set>
	</equipo>
  </partido>
  <partido>
	<fecha>2 AGO</fecha>
	<hora>22:00</hora>
	<categoria>AFM</categoria>
	<grupo>A</grupo>
	<fase>LIGA</fase>
	<equipo>
	  <nombre>Rodrigo Rodrigo</nombre>
	  <set number="1">5</set>
	  <set number="2">3</set>
	  <set number="3">0</set>
	</equipo>
	<equipo>
	  <nombre>Colacao Con Leche</nombre>
	  <set number="1">15</set>
	  <set number="2">15</set>
	  <set number="3">0</set>
	</equipo>
  </partido>
  <partido>
	<fecha>2 AGO</fecha>
	<hora>22:30</hora>
	<categoria>AFM</categoria>
	<grupo>B</grupo>
	<fase>LIGA</fase>
	<equipo>
	  <nombre>Churricarri</nombre>
	  <set number="1">7</set>
	  <set number="2">12</set>
	  <set number="3">0</set>
	</equipo>
	<equipo>
	  <nombre>Illescas Gallego</nombre>
	  <set number="1">15</set>
	  <set number="2">15</set>
	  <set number="3">0</set>
	</equipo>
  </partido>
  <partido>
	<fecha>2 AGO</fecha>
	<hora>23:00</hora>
	<categoria>AFM</categoria>
	<grupo>A</grupo>
	<fase>LIGA</fase>
	<equipo>
	  <nombre>Alberto Y Ángela</nombre>
	  <set number="1">0</set>
	  <set number="2">0</set>
	  <set number="3">0</set>
	</equipo>
	<equipo>
	  <nombre>Candela Donate</nombre>
	  <set number="1">15</set>
	  <set number="2">15</set>
	  <set number="3">0</set>
	</equipo>
  </partido>
  <partido>
	<fecha>2 AGO</fecha>
	<hora>23:30</hora>
	<categoria>AFI</categoria>
	<grupo>J</grupo>
	<fase>LIGA</fase>
	<equipo>
	  <nombre>Los Finger</nombre>
	  <set number="1">4</set>
	  <set number="2">5</set>
	  <set number="3">0</set>
	</equipo>
	<equipo>
	  <nombre>Morcillo De La Cruz</nombre>
	  <set number="1">15</set>
	  <set number="2">15</set>
	  <set number="3">0</set>
	</equipo>
  </partido>
  <partido>
	<fecha>2 AGO</fecha>
	<hora>01:00</hora>
	<categoria>AFM</categoria>
	<grupo>B</grupo>
	<fase>LIGA</fase>
	<equipo>
	  <nombre>Illescas Gallego</nombre>
	  <set number="1">6</set>
	  <set number="2">12</set>
	  <set number="3">0</set>
	</equipo>
	<equipo>
	  <nombre>Álvaro Y Noe</nombre>
	  <set number="1">15</set>
	  <set number="2">15</set>
	  <set number="3">0</set>
	</equipo>
  </partido>
  <partido>
	<fecha>2 AGO</fecha>
	<hora>00:30</hora>
	<categoria>AFM</categoria>
	<grupo>A</grupo>
	<fase>LIGA</fase>
	<equipo>
	  <nombre>Alberto Y Ángela</nombre>
	  <set number="1">0</set>
	  <set number="2">0</set>
	  <set number="3">0</set>
	</equipo>
	<equipo>
	  <nombre>Rodrigo Rodrigo</nombre>
	  <set number="1">15</set>
	  <set number="2">15</set>
	  <set number="3">0</set>
	</equipo>
  </partido>
  <partido>
	<fecha>2 AGO</fecha>
	<hora>01:30</hora>
	<categoria>AFI</categoria>
	<grupo>J</grupo>
	<fase>LIGA</fase>
	<equipo>
	  <nombre>Morcillo De La Cruz</nombre>
	  <set number="1">15</set>
	  <set number="2">15</set>
	  <set number="3">0</set>
	</equipo>
	<equipo>
	  <nombre>Grupo Norte</nombre>
	  <set number="1">4</set>
	  <set number="2">6</set>
	  <set number="3">0</set>
	</equipo>
  </partido>
  <partido>
	<fecha>2 AGO</fecha>
	<hora>23:15</hora>
	<categoria>AFI</categoria>
	<grupo>D</grupo>
	<fase>LIGA</fase>
	<equipo>
	  <nombre>Viejas Glorias</nombre>
	  <set number="1">4</set>
	  <set number="2">7</set>
	  <set number="3">0</set>
	</equipo>
	<equipo>
	  <nombre>Jumping Crew</nombre>
	  <set number="1">15</set>
	  <set number="2">15</set>
	  <set number="3">0</set>
	</equipo>
  </partido>
  <partido>
	<fecha>2 AGO</fecha>
	<hora>19:30</hora>
	<categoria>MIX</categoria>
	<grupo>C</grupo>
	<fase>LIGA</fase>
	<equipo>
	  <nombre>Cortés García</nombre>
	  <set number="1">7</set>
	  <set number="2">7</set>
	  <set number="3">0</set>
	</equipo>
	<equipo>
	  <nombre>Toribio Cañizares</nombre>
	  <set number="1">15</set>
	  <set number="2">15</set>
	  <set number="3">0</set>
	</equipo>
  </partido>
  <partido>
	<fecha>2 AGO</fecha>
	<hora>20:00</hora>
	<categoria>MIX</categoria>
	<grupo>E</grupo>
	<fase>LIGA</fase>
	<equipo>
	  <nombre>Cortés Rodado</nombre>
	  <set number="1">15</set>
	  <set number="2">15</set>
	  <set number="3">0</set>
	</equipo>
	<equipo>
	  <nombre>Noé Leti</nombre>
	  <set number="1">13</set>
	  <set number="2">9</set>
	  <set number="3">0</set>
	</equipo>
  </partido>
  <partido>
	<fecha>2 AGO</fecha>
	<hora>21:00</hora>
	<categoria>MIX</categoria>
	<grupo>E</grupo>
	<fase>LIGA</fase>
	<equipo>
	  <nombre>Astilleros Rojas</nombre>
	  <set number="1">15</set>
	  <set number="2">15</set>
	  <set number="3">0</set>
	</equipo>
	<equipo>
	  <nombre>Noé Leti</nombre>
	  <set number="1">7</set>
	  <set number="2">11</set>
	  <set number="3">0</set>
	</equipo>
  </partido>
  <partido>
	<fecha>2 AGO</fecha>
	<hora>01:30</hora>
	<categoria>AFI</categoria>
	<grupo>F</grupo>
	<fase>LIGA</fase>
	<equipo>
	  <nombre>Andrés Y Sergio</nombre>
	  <set number="1">12</set>
	  <set number="2">17</set>
	  <set number="3">8</set>
	</equipo>
	<equipo>
	  <nombre>Gatuli Kulkin</nombre>
	  <set number="1">15</set>
	  <set number="2">15</set>
	  <set number="3">11</set>
	</equipo>
  </partido>
  <partido>
	<fecha>2 AGO</fecha>
	<hora>22:00</hora>
	<categoria>AFI</categoria>
	<grupo>J</grupo>
	<fase>LIGA</fase>
	<equipo>
	  <nombre>Agapito Y Juanfri</nombre>
	  <set number="1">15</set>
	  <set number="2">15</set>
	  <set number="3">0</set>
	</equipo>
	<equipo>
	  <nombre>Grupo Norte</nombre>
	  <set number="1">8</set>
	  <set number="2">6</set>
	  <set number="3">0</set>
	</equipo>
  </partido>
  <partido>
	<fecha>2 AGO</fecha>
	<hora>22:30</hora>
	<categoria>AFI</categoria>
	<grupo>H</grupo>
	<fase>LIGA</fase>
	<equipo>
	  <nombre>Vargas Me Mira</nombre>
	  <set number="1">15</set>
	  <set number="2">15</set>
	  <set number="3">0</set>
	</equipo>
	<equipo>
	  <nombre>Hervás Rodrigo</nombre>
	  <set number="1">12</set>
	  <set number="2">9</set>
	  <set number="3">0</set>
	</equipo>
  </partido>
  <partido>
	<fecha>2 AGO</fecha>
	<hora>23:00</hora>
	<categoria>FEM</categoria>
	<grupo>B</grupo>
	<fase>LIGA</fase>
	<equipo>
	  <nombre>El Retorno De Antonia</nombre>
	  <set number="1">7</set>
	  <set number="2">5</set>
	  <set number="3">0</set>
	</equipo>
	<equipo>
	  <nombre>Mora Peco</nombre>
	  <set number="1">15</set>
	  <set number="2">15</set>
	  <set number="3">0</set>
	</equipo>
  </partido>
  <partido>
	<fecha>2 AGO</fecha>
	<hora>23:30</hora>
	<categoria>AFI</categoria>
	<grupo>F</grupo>
	<fase>LIGA</fase>
	<equipo>
	  <nombre>Andrés Y Sergio</nombre>
	  <set number="1">15</set>
	  <set number="2">15</set>
	  <set number="3">0</set>
	</equipo>
	<equipo>
	  <nombre>Los Bilowos</nombre>
	  <set number="1">10</set>
	  <set number="2">6</set>
	  <set number="3">0</set>
	</equipo>
  </partido>
  <partido>
	<fecha>2 AGO</fecha>
	<hora>00:00</hora>
	<categoria>MIX</categoria>
	<grupo>C</grupo>
	<fase>LIGA</fase>
	<equipo>
	  <nombre>Arévalo Mora</nombre>
	  <set number="1">15</set>
	  <set number="2">13</set>
	  <set number="3">6</set>
	</equipo>
	<equipo>
	  <nombre>Toribio Cañizares</nombre>
	  <set number="1">13</set>
	  <set number="2">15</set>
	  <set number="3">11</set>
	</equipo>
  </partido>
  <partido>
	<fecha>2 AGO</fecha>
	<hora>20:00</hora>
	<categoria>AFI</categoria>
	<grupo>C</grupo>
	<fase>LIGA</fase>
	<equipo>
	  <nombre>Jungle Fever</nombre>
	  <set number="1">15</set>
	  <set number="2">15</set>
	  <set number="3">0</set>
	</equipo>
	<equipo>
	  <nombre>Masturbaladilla</nombre>
	  <set number="1">11</set>
	  <set number="2">6</set>
	  <set number="3">0</set>
	</equipo>
  </partido>
  <partido>
	<fecha>3 AGO</fecha>
	<hora>18:30</hora>
	<categoria>AFI</categoria>
	<grupo>F</grupo>
	<fase>LIGA</fase>
	<equipo>
	  <nombre>Rafa Y Óscar</nombre>
	  <set number="1">15</set>
	  <set number="2">15</set>
	  <set number="3">0</set>
	</equipo>
	<equipo>
	  <nombre>Los Bilowos</nombre>
	  <set number="1">7</set>
	  <set number="2">13</set>
	  <set number="3">0</set>
	</equipo>
  </partido>
  <partido>
	<fecha>3 AGO</fecha>
	<hora>19:00</hora>
	<categoria>AFI</categoria>
	<grupo>J</grupo>
	<fase>LIGA</fase>
	<equipo>
	  <nombre>Los Finger</nombre>
	  <set number="1">15</set>
	  <set number="2">15</set>
	  <set number="3">0</set>
	</equipo>
	<equipo>
	  <nombre>Grupo Norte</nombre>
	  <set number="1">8</set>
	  <set number="2">11</set>
	  <set number="3">0</set>
	</equipo>
  </partido>
  <partido>
	<fecha>3 AGO</fecha>
	<hora>23:30</hora>
	<categoria>AFI</categoria>
	<grupo>A</grupo>
	<fase>LIGA</fase>
	<equipo>
	  <nombre>Hermanos Martín</nombre>
	  <set number="1">15</set>
	  <set number="2">15</set>
	  <set number="3">0</set>
	</equipo>
	<equipo>
	  <nombre>0.30 PVP</nombre>
	  <set number="1">10</set>
	  <set number="2">4</set>
	  <set number="3">0</set>
	</equipo>
  </partido>
  <partido>
	<fecha>3 AGO</fecha>
	<hora>20:00</hora>
	<categoria>AFM</categoria>
	<grupo>B</grupo>
	<fase>LIGA</fase>
	<equipo>
	  <nombre>Chini Gloria</nombre>
	  <set number="1">9</set>
	  <set number="2">7</set>
	  <set number="3">0</set>
	</equipo>
	<equipo>
	  <nombre>Churricarri</nombre>
	  <set number="1">15</set>
	  <set number="2">15</set>
	  <set number="3">0</set>
	</equipo>
  </partido>
  <partido>
	<fecha>3 AGO</fecha>
	<hora>20:30</hora>
	<categoria>AFI</categoria>
	<grupo>H</grupo>
	<fase>LIGA</fase>
	<equipo>
	  <nombre>Mandril Y Comadreja</nombre>
	  <set number="1">15</set>
	  <set number="2">15</set>
	  <set number="3">0</set>
	</equipo>
	<equipo>
	  <nombre>Hervás Rodrigo</nombre>
	  <set number="1">10</set>
	  <set number="2">13</set>
	  <set number="3">0</set>
	</equipo>
  </partido>
  <partido>
	<fecha>3 AGO</fecha>
	<hora>21:30</hora>
	<categoria>AFI</categoria>
	<grupo>I</grupo>
	<fase>LIGA</fase>
	<equipo>
	  <nombre>Rojas Casas</nombre>
	  <set number="1">15</set>
	  <set number="2">15</set>
	  <set number="3">0</set>
	</equipo>
	<equipo>
	  <nombre>Los Desastres Del Día 3</nombre>
	  <set number="1">6</set>
	  <set number="2">6</set>
	  <set number="3">0</set>
	</equipo>
  </partido>
  <partido>
	<fecha>3 AGO</fecha>
	<hora>22:00</hora>
	<categoria>MAS</categoria>
	<grupo>D</grupo>
	<fase>LIGA</fase>
	<equipo>
	  <nombre>Fer Y Sergi</nombre>
	  <set number="1">15</set>
	  <set number="2">15</set>
	  <set number="3">0</set>
	</equipo>
	<equipo>
	  <nombre>Anoelin Y Guzmalín</nombre>
	  <set number="1">13</set>
	  <set number="2">13</set>
	  <set number="3">0</set>
	</equipo>
  </partido>
  <partido>
	<fecha>3 AGO</fecha>
	<hora>22:30</hora>
	<categoria>AFI</categoria>
	<grupo>J</grupo>
	<fase>LIGA</fase>
	<equipo>
	  <nombre>Agapito Y Juanfri</nombre>
	  <set number="1">10</set>
	  <set number="2">6</set>
	  <set number="3">0</set>
	</equipo>
	<equipo>
	  <nombre>Morcillo De La Cruz</nombre>
	  <set number="1">15</set>
	  <set number="2">15</set>
	  <set number="3">0</set>
	</equipo>
  </partido>
  <partido>
	<fecha>3 AGO</fecha>
	<hora>23:00</hora>
	<categoria>AFI</categoria>
	<grupo>I</grupo>
	<fase>LIGA</fase>
	<equipo>
	  <nombre>All Stars</nombre>
	  <set number="1">3</set>
	  <set number="2">10</set>
	  <set number="3">0</set>
	</equipo>
	<equipo>
	  <nombre>Ruano Rodrigo</nombre>
	  <set number="1">15</set>
	  <set number="2">15</set>
	  <set number="3">0</set>
	</equipo>
  </partido>
  <partido>
	<fecha>3 AGO</fecha>
	<hora>00:00</hora>
	<categoria>MIX</categoria>
	<grupo>C</grupo>
	<fase>LIGA</fase>
	<equipo>
	  <nombre>Nieto Díaz</nombre>
	  <set number="1">14</set>
	  <set number="2">15</set>
	  <set number="3">16</set>
	</equipo>
	<equipo>
	  <nombre>Toribio Cañizares</nombre>
	  <set number="1">16</set>
	  <set number="2">13</set>
	  <set number="3">18</set>
	</equipo>
  </partido>
  <partido>
	<fecha>3 AGO</fecha>
	<hora>00:30</hora>
	<categoria>AFI</categoria>
	<grupo>H</grupo>
	<fase>LIGA</fase>
	<equipo>
	  <nombre>Vargas Me Mira</nombre>
	  <set number="1">15</set>
	  <set number="2">11</set>
	  <set number="3">5</set>
	</equipo>
	<equipo>
	  <nombre>Antonio Y Ramón</nombre>
	  <set number="1">11</set>
	  <set number="2">15</set>
	  <set number="3">11</set>
	</equipo>
  </partido>
  <partido>
	<fecha>3 AGO</fecha>
	<hora>18:00</hora>
	<categoria>AFM</categoria>
	<grupo>B</grupo>
	<fase>LIGA</fase>
	<equipo>
	  <nombre>Chini Gloria</nombre>
	  <set number="1">4</set>
	  <set number="2">6</set>
	  <set number="3">0</set>
	</equipo>
	<equipo>
	  <nombre>Álvaro Y Noe</nombre>
	  <set number="1">15</set>
	  <set number="2">15</set>
	  <set number="3">0</set>
	</equipo>
  </partido>
  <partido>
	<fecha>3 AGO</fecha>
	<hora>19:00</hora>
	<categoria>AFM</categoria>
	<grupo>B</grupo>
	<fase>LIGA</fase>
	<equipo>
	  <nombre>Chini Gloria</nombre>
	  <set number="1">6</set>
	  <set number="2">6</set>
	  <set number="3">0</set>
	</equipo>
	<equipo>
	  <nombre>El Punto Y La I</nombre>
	  <set number="1">15</set>
	  <set number="2">15</set>
	  <set number="3">0</set>
	</equipo>
  </partido>
  <partido>
	<fecha>3 AGO</fecha>
	<hora>19:30</hora>
	<categoria>AFI</categoria>
	<grupo>B</grupo>
	<fase>LIGA</fase>
	<equipo>
	  <nombre>El Rolón Volador</nombre>
	  <set number="1">15</set>
	  <set number="2">11</set>
	  <set number="3">11</set>
	</equipo>
	<equipo>
	  <nombre>Rastrerismos</nombre>
	  <set number="1">5</set>
	  <set number="2">15</set>
	  <set number="3">7</set>
	</equipo>
  </partido>
  <partido>
	<fecha>3 AGO</fecha>
	<hora>20:00</hora>
	<categoria>AFI</categoria>
	<grupo>E</grupo>
	<fase>LIGA</fase>
	<equipo>
	  <nombre>Jaime Y Manu</nombre>
	  <set number="1">5</set>
	  <set number="2">4</set>
	  <set number="3">0</set>
	</equipo>
	<equipo>
	  <nombre>Los Dalton</nombre>
	  <set number="1">15</set>
	  <set number="2">15</set>
	  <set number="3">0</set>
	</equipo>
  </partido>
  <partido>
	<fecha>3 AGO</fecha>
	<hora>20:30</hora>
	<categoria>MIX</categoria>
	<grupo>A</grupo>
	<fase>LIGA</fase>
	<equipo>
	  <nombre>Carretero Monroy</nombre>
	  <set number="1">15</set>
	  <set number="2">15</set>
	  <set number="3">0</set>
	</equipo>
	<equipo>
	  <nombre>Hervás Loro</nombre>
	  <set number="1">9</set>
	  <set number="2">9</set>
	  <set number="3">0</set>
	</equipo>
  </partido>
  <partido>
	<fecha>3 AGO</fecha>
	<hora>21:00</hora>
	<categoria>AFM</categoria>
	<grupo>D</grupo>
	<fase>LIGA</fase>
	<equipo>
	  <nombre>Colacao Con Leche</nombre>
	  <set number="1">15</set>
	  <set number="2">15</set>
	  <set number="3">0</set>
	</equipo>
	<equipo>
	  <nombre>
	  Illescas Gallego  </nombre>
	  <set number="1">13</set>
	  <set number="2">11</set>
	  <set number="3">0</set>
	</equipo>
  </partido>
  <partido>
	<fecha>3 AGO</fecha>
	<hora>21:30</hora>
	<categoria>AFM</categoria>
	<grupo>D</grupo>
	<fase>LIGA</fase>
	<equipo>
	  <nombre>Álvaro Y Noe</nombre>
	  <set number="1">15</set>
	  <set number="2">15</set>
	  <set number="3">0</set>
	</equipo>
	<equipo>
	  <nombre>
	  Candela Donate</nombre>
	  <set number="1">5</set>
	  <set number="2">10</set>
	  <set number="3">0</set>
	</equipo>
  </partido>
  <partido>
	<fecha>3 AGO</fecha>
	<hora>23:30</hora>
	<categoria>AFM</categoria>
	<grupo>D</grupo>
	<fase>LIGA</fase>
	<equipo>
	  <nombre>Candela Donate</nombre>
	  <set number="1">14</set>
	  <set number="2">12</set>
	  <set number="3">0</set>
	</equipo>
	<equipo>
	  <nombre>
	  Illescas Gallego  </nombre>
	  <set number="1">16</set>
	  <set number="2">15</set>
	  <set number="3">0</set>
	</equipo>
  </partido>
  <partido>
	<fecha>3 AGO</fecha>
	<hora>00:00</hora>
	<categoria>AFM</categoria>
	<grupo>D</grupo>
	<fase>LIGA</fase>
	<equipo>
	  <nombre>Álvaro Y Noe</nombre>
	  <set number="1">15</set>
	  <set number="2">15</set>
	  <set number="3">0</set>
	</equipo>
	<equipo>
	  <nombre>
	  Colacao Con Leche</nombre>
	  <set number="1">13</set>
	  <set number="2">11</set>
	  <set number="3">0</set>
	</equipo>
  </partido>
  <partido>
	<fecha>3 AGO</fecha>
	<hora>17:30</hora>
	<categoria>AFM</categoria>
	<grupo>B</grupo>
	<fase>LIGA</fase>
	<equipo>
	  <nombre>Chini Gloria</nombre>
	  <set number="1">6</set>
	  <set number="2">6</set>
	  <set number="3">0</set>
	</equipo>
	<equipo>
	  <nombre>Illescas Gallego</nombre>
	  <set number="1">15</set>
	  <set number="2">15</set>
	  <set number="3">0</set>
	</equipo>
  </partido>
  <partido>
	<fecha>3 AGO</fecha>
	<hora>11:00</hora>
	<categoria>FEM</categoria>
	<grupo>B</grupo>
	<fase>LIGA</fase>
	<equipo>
	  <nombre>El Retorno De Antonia</nombre>
	  <set number="1">4</set>
	  <set number="2">5</set>
	  <set number="3">0</set>
	</equipo>
	<equipo>
	  <nombre>Rojas Sánchez</nombre>
	  <set number="1">15</set>
	  <set number="2">15</set>
	  <set number="3">0</set>
	</equipo>
  </partido>
  <partido>
	<fecha>3 AGO</fecha>
	<hora>19:30</hora>
	<categoria>MIX</categoria>
	<grupo>C</grupo>
	<fase>LIGA</fase>
	<equipo>
	  <nombre>Nieto Díaz</nombre>
	  <set number="1">15</set>
	  <set number="2">15</set>
	  <set number="3">0</set>
	</equipo>
	<equipo>
	  <nombre>Cortés García</nombre>
	  <set number="1">6</set>
	  <set number="2">8</set>
	  <set number="3">0</set>
	</equipo>
  </partido>
  <partido>
	<fecha>3 AGO</fecha>
	<hora>12:00</hora>
	<categoria>AFM</categoria>
	<grupo>A</grupo>
	<fase>LIGA</fase>
	<equipo>
	  <nombre>Colacao Con Leche</nombre>
	  <set number="1">15</set>
	  <set number="2">15</set>
	  <set number="3">0</set>
	</equipo>
	<equipo>
	  <nombre>Alberto Y Ángela</nombre>
	  <set number="1">0</set>
	  <set number="2">0</set>
	  <set number="3">0</set>
	</equipo>
  </partido>
  <partido>
	<fecha>4 AGO</fecha>
	<hora>20:00</hora>
	<categoria>AFI</categoria>
	<grupo>E</grupo>
	<fase>LIGA</fase>
	<equipo>
	  <nombre>Vicsa Electricidad</nombre>
	  <set number="1">15</set>
	  <set number="2">15</set>
	  <set number="3">0</set>
	</equipo>
	<equipo>
	  <nombre>Los Dalton</nombre>
	  <set number="1">7</set>
	  <set number="2">7</set>
	  <set number="3">0</set>
	</equipo>
  </partido>
  <partido>
	<fecha>4 AGO</fecha>
	<hora>20:00</hora>
	<categoria>AFI</categoria>
	<grupo>I</grupo>
	<fase>LIGA</fase>
	<equipo>
	  <nombre>All Stars</nombre>
	  <set number="1">9</set>
	  <set number="2">9</set>
	  <set number="3">0</set>
	</equipo>
	<equipo>
	  <nombre>Rojas Casas</nombre>
	  <set number="1">15</set>
	  <set number="2">15</set>
	  <set number="3">0</set>
	</equipo>
  </partido>
  <partido>
	<fecha>4 AGO</fecha>
	<hora>20:30</hora>
	<categoria>AFI</categoria>
	<grupo>G</grupo>
	<fase>LIGA</fase>
	<equipo>
	  <nombre>No Loves Me No Party</nombre>
	  <set number="1">7</set>
	  <set number="2">4</set>
	  <set number="3">0</set>
	</equipo>
	<equipo>
	  <nombre>The Cousins</nombre>
	  <set number="1">15</set>
	  <set number="2">15</set>
	  <set number="3">0</set>
	</equipo>
  </partido>
  <partido>
	<fecha>4 AGO</fecha>
	<hora>21:00</hora>
	<categoria>AFI</categoria>
	<grupo>C</grupo>
	<fase>LIGA</fase>
	<equipo>
	  <nombre>Jungle Fever</nombre>
	  <set number="1">15</set>
	  <set number="2">15</set>
	  <set number="3">0</set>
	</equipo>
	<equipo>
	  <nombre>Frente Polisario</nombre>
	  <set number="1">4</set>
	  <set number="2">7</set>
	  <set number="3">0</set>
	</equipo>
  </partido>
  <partido>
	<fecha>4 AGO</fecha>
	<hora>21:30</hora>
	<categoria>AFI</categoria>
	<grupo>G</grupo>
	<fase>LIGA</fase>
	<equipo>
	  <nombre>Guti Y Yeste</nombre>
	  <set number="1">15</set>
	  <set number="2">15</set>
	  <set number="3">0</set>
	</equipo>
	<equipo>
	  <nombre>Alberto Y Javier</nombre>
	  <set number="1">5</set>
	  <set number="2">13</set>
	  <set number="3">0</set>
	</equipo>
  </partido>
  <partido>
	<fecha>4 AGO</fecha>
	<hora>23:30</hora>
	<categoria>AFI</categoria>
	<grupo>E</grupo>
	<fase>LIGA</fase>
	<equipo>
	  <nombre>Vicsa Electricidad</nombre>
	  <set number="1">15</set>
	  <set number="2">15</set>
	  <set number="3">0</set>
	</equipo>
	<equipo>
	  <nombre>Jaime Y Manu</nombre>
	  <set number="1">3</set>
	  <set number="2">5</set>
	  <set number="3">0</set>
	</equipo>
  </partido>
  <partido>
	<fecha>4 AGO</fecha>
	<hora>22:30</hora>
	<categoria>AFI</categoria>
	<grupo>D</grupo>
	<fase>LIGA</fase>
	<equipo>
	  <nombre>Viejas Glorias</nombre>
	  <set number="1">13</set>
	  <set number="2">10</set>
	  <set number="3">0</set>
	</equipo>
	<equipo>
	  <nombre>González Lorente</nombre>
	  <set number="1">15</set>
	  <set number="2">15</set>
	  <set number="3">0</set>
	</equipo>
  </partido>
  <partido>
	<fecha>4 AGO</fecha>
	<hora>23:00</hora>
	<categoria>AFI</categoria>
	<grupo>G</grupo>
	<fase>LIGA</fase>
	<equipo>
	  <nombre>The Cousins</nombre>
	  <set number="1">17</set>
	  <set number="2">15</set>
	  <set number="3">0</set>
	</equipo>
	<equipo>
	  <nombre>Alberto Y Javier</nombre>
	  <set number="1">15</set>
	  <set number="2">9</set>
	  <set number="3">0</set>
	</equipo>
  </partido>
  <partido>
	<fecha>4 AGO</fecha>
	<hora>23:30</hora>
	<categoria>AFI</categoria>
	<grupo>C</grupo>
	<fase>LIGA</fase>
	<equipo>
	  <nombre>Jungle Fever</nombre>
	  <set number="1">15</set>
	  <set number="2">16</set>
	  <set number="3">0</set>
	</equipo>
	<equipo>
	  <nombre>Alioli</nombre>
	  <set number="1">5</set>
	  <set number="2">14</set>
	  <set number="3">0</set>
	</equipo>
  </partido>
  <partido>
	<fecha>4 AGO</fecha>
	<hora>00:00</hora>
	<categoria>AFI</categoria>
	<grupo>A</grupo>
	<fase>LIGA</fase>
	<equipo>
	  <nombre>Candela Rodrigo</nombre>
	  <set number="1">15</set>
	  <set number="2">15</set>
	  <set number="3">0</set>
	</equipo>
	<equipo>
	  <nombre>0.30 PVP</nombre>
	  <set number="1">7</set>
	  <set number="2">10</set>
	  <set number="3">0</set>
	</equipo>
  </partido>
  <partido>
	<fecha>4 AGO</fecha>
	<hora>00:30</hora>
	<categoria>AFI</categoria>
	<grupo>G</grupo>
	<fase>LIGA</fase>
	<equipo>
	  <nombre>Guti Y Yeste</nombre>
	  <set number="1">15</set>
	  <set number="2">15</set>
	  <set number="3">0</set>
	</equipo>
	<equipo>
	  <nombre>No Loves Me No Party</nombre>
	  <set number="1">5</set>
	  <set number="2">7</set>
	  <set number="3">0</set>
	</equipo>
  </partido>
  <partido>
	<fecha>4 AGO</fecha>
	<hora>20:30</hora>
	<categoria>AFI</categoria>
	<grupo>K</grupo>
	<fase>LIGA</fase>
	<equipo>
	  <nombre>Chori Y Paco</nombre>
	  <set number="1">16</set>
	  <set number="2">15</set>
	  <set number="3">0</set>
	</equipo>
	<equipo>
	  <nombre>Alaska Y Vaquerizo</nombre>
	  <set number="1">14</set>
	  <set number="2">12</set>
	  <set number="3">0</set>
	</equipo>
  </partido>
  <partido>
	<fecha>4 AGO</fecha>
	<hora>21:00</hora>
	<categoria>MAS</categoria>
	<grupo>C</grupo>
	<fase>LIGA</fase>
	<equipo>
	  <nombre>Beldad Pozo</nombre>
	  <set number="1">15</set>
	  <set number="2">15</set>
	  <set number="3">0</set>
	</equipo>
	<equipo>
	  <nombre>Nieto Brígido</nombre>
	  <set number="1">6</set>
	  <set number="2">10</set>
	  <set number="3">0</set>
	</equipo>
  </partido>
  <partido>
	<fecha>5 AGO</fecha>
	<hora>21:30</hora>
	<categoria>AFI</categoria>
	<grupo>B</grupo>
	<fase>LIGA</fase>
	<equipo>
	  <nombre>Chinato Y Enrique</nombre>
	  <set number="1">2</set>
	  <set number="2">4</set>
	  <set number="3">0</set>
	</equipo>
	<equipo>
	  <nombre>Los Del Rodeo</nombre>
	  <set number="1">15</set>
	  <set number="2">15</set>
	  <set number="3">0</set>
	</equipo>
  </partido>
  <partido>
	<fecha>4 AGO</fecha>
	<hora>22:30</hora>
	<categoria>AFI</categoria>
	<grupo>K</grupo>
	<fase>LIGA</fase>
	<equipo>
	  <nombre>Chori Y Paco</nombre>
	  <set number="1">9</set>
	  <set number="2">13</set>
	  <set number="3">0</set>
	</equipo>
	<equipo>
	  <nombre>La Catapulta Infernal</nombre>
	  <set number="1">15</set>
	  <set number="2">15</set>
	  <set number="3">0</set>
	</equipo>
  </partido>
  <partido>
	<fecha>4 AGO</fecha>
	<hora>23:00</hora>
	<categoria>MAS</categoria>
	<grupo>C</grupo>
	<fase>LIGA</fase>
	<equipo>
	  <nombre>Beldad Pozo</nombre>
	  <set number="1">15</set>
	  <set number="2">15</set>
	  <set number="3">0</set>
	</equipo>
	<equipo>
	  <nombre>Sánchez Parreño</nombre>
	  <set number="1">11</set>
	  <set number="2">11</set>
	  <set number="3">0</set>
	</equipo>
  </partido>
  <partido>
	<fecha>4 AGO</fecha>
	<hora>22:00</hora>
	<categoria>AFI</categoria>
	<grupo>A</grupo>
	<fase>LIGA</fase>
	<equipo>
	  <nombre>Illescas Punzón</nombre>
	  <set number="1">17</set>
	  <set number="2">15</set>
	  <set number="3">5</set>
	</equipo>
	<equipo>
	  <nombre>Candela Rodrigo</nombre>
	  <set number="1">15</set>
	  <set number="2">7</set>
	  <set number="3">11</set>
	</equipo>
  </partido>
  <partido>
	<fecha>4 AGO</fecha>
	<hora>00:00</hora>
	<categoria>MAS</categoria>
	<grupo>C</grupo>
	<fase>LIGA</fase>
	<equipo>
	  <nombre>Nieto Brígido</nombre>
	  <set number="1">15</set>
	  <set number="2">16</set>
	  <set number="3">0</set>
	</equipo>
	<equipo>
	  <nombre>Sánchez Parreño</nombre>
	  <set number="1">10</set>
	  <set number="2">14</set>
	  <set number="3">0</set>
	</equipo>
  </partido>
  <partido>
	<fecha>4 AGO</fecha>
	<hora>00:30</hora>
	<categoria>AFI</categoria>
	<grupo>D</grupo>
	<fase>LIGA</fase>
	<equipo>
	  <nombre>González Lorente</nombre>
	  <set number="1">15</set>
	  <set number="2">15</set>
	  <set number="3">0</set>
	</equipo>
	<equipo>
	  <nombre>Albertonuels</nombre>
	  <set number="1">13</set>
	  <set number="2">13</set>
	  <set number="3">0</set>
	</equipo>
  </partido>
  <partido>
	<fecha>5 AGO</fecha>
	<hora>19:30</hora>
	<categoria>AFI</categoria>
	<grupo>G</grupo>
	<fase>LIGA</fase>
	<equipo>
	  <nombre>The Cousins</nombre>
	  <set number="1">15</set>
	  <set number="2">6</set>
	  <set number="3">7</set>
	</equipo>
	<equipo>
	  <nombre>Guti Y Yeste</nombre>
	  <set number="1">13</set>
	  <set number="2">15</set>
	  <set number="3">11</set>
	</equipo>
  </partido>
  <partido>
	<fecha>5 AGO</fecha>
	<hora>20:00</hora>
	<categoria>AFI</categoria>
	<grupo>E</grupo>
	<fase>LIGA</fase>
	<equipo>
	  <nombre>Vicsa Electricidad</nombre>
	  <set number="1">15</set>
	  <set number="2">15</set>
	  <set number="3">0</set>
	</equipo>
	<equipo>
	  <nombre>Álvaro Y Carlos</nombre>
	  <set number="1">5</set>
	  <set number="2">9</set>
	  <set number="3">0</set>
	</equipo>
  </partido>
  <partido>
	<fecha>5 AGO</fecha>
	<hora>23:00</hora>
	<categoria>MIX</categoria>
	<grupo>E</grupo>
	<fase>LIGA</fase>
	<equipo>
	  <nombre>González Peco</nombre>
	  <set number="1">12</set>
	  <set number="2">21</set>
	  <set number="3">12</set>
	</equipo>
	<equipo>
	  <nombre>Noé Leti</nombre>
	  <set number="1">15</set>
	  <set number="2">19</set>
	  <set number="3">10</set>
	</equipo>
  </partido>
  <partido>
	<fecha>5 AGO</fecha>
	<hora>21:00</hora>
	<categoria>AFI</categoria>
	<grupo>A</grupo>
	<fase>LIGA</fase>
	<equipo>
	  <nombre>Illescas Punzón</nombre>
	  <set number="1">15</set>
	  <set number="2">15</set>
	  <set number="3">0</set>
	</equipo>
	<equipo>
	  <nombre>0.30 PVP</nombre>
	  <set number="1">10</set>
	  <set number="2">8</set>
	  <set number="3">0</set>
	</equipo>
  </partido>
  <partido>
	<fecha>5 AGO</fecha>
	<hora>21:30</hora>
	<categoria>AFI</categoria>
	<grupo>G</grupo>
	<fase>LIGA</fase>
	<equipo>
	  <nombre>No Loves Me No Party</nombre>
	  <set number="1">8</set>
	  <set number="2">12</set>
	  <set number="3">0</set>
	</equipo>
	<equipo>
	  <nombre>Alberto Y Javier</nombre>
	  <set number="1">15</set>
	  <set number="2">15</set>
	  <set number="3">0</set>
	</equipo>
  </partido>
  <partido>
	<fecha>5 AGO</fecha>
	<hora>22:00</hora>
	<categoria>AFI</categoria>
	<grupo>D</grupo>
	<fase>LIGA</fase>
	<equipo>
	  <nombre>González Lorente</nombre>
	  <set number="1">6</set>
	  <set number="2">10</set>
	  <set number="3">0</set>
	</equipo>
	<equipo>
	  <nombre>Jumping Crew</nombre>
	  <set number="1">15</set>
	  <set number="2">15</set>
	  <set number="3">0</set>
	</equipo>
  </partido>
  <partido>
	<fecha>5 AGO</fecha>
	<hora>22:30</hora>
	<categoria>MAS</categoria>
	<grupo>D</grupo>
	<fase>LIGA</fase>
	<equipo>
	  <nombre>Arévalo Toribio</nombre>
	  <set number="1">15</set>
	  <set number="2">15</set>
	  <set number="3">0</set>
	</equipo>
	<equipo>
	  <nombre>Anoelin Y Guzmalín</nombre>
	  <set number="1">11</set>
	  <set number="2">12</set>
	  <set number="3">0</set>
	</equipo>
  </partido>
  <partido>
	<fecha>5 AGO</fecha>
	<hora>23:00</hora>
	<categoria>AFI</categoria>
	<grupo>K</grupo>
	<fase>LIGA</fase>
	<equipo>
	  <nombre>Bastante Gómez</nombre>
	  <set number="1">15</set>
	  <set number="2">15</set>
	  <set number="3">0</set>
	</equipo>
	<equipo>
	  <nombre>Chori Y Paco</nombre>
	  <set number="1">8</set>
	  <set number="2">12</set>
	  <set number="3">0</set>
	</equipo>
  </partido>
  <partido>
	<fecha>5 AGO</fecha>
	<hora>23:30</hora>
	<categoria>AFI</categoria>
	<grupo>C</grupo>
	<fase>LIGA</fase>
	<equipo>
	  <nombre>Alioli</nombre>
	  <set number="1">15</set>
	  <set number="2">15</set>
	  <set number="3">0</set>
	</equipo>
	<equipo>
	  <nombre>Masturbaladilla</nombre>
	  <set number="1">4</set>
	  <set number="2">8</set>
	  <set number="3">0</set>
	</equipo>
  </partido>
  <partido>
	<fecha>5 AGO</fecha>
	<hora>00:00</hora>
	<categoria>MAS</categoria>
	<grupo>B</grupo>
	<fase>LIGA</fase>
	<equipo>
	  <nombre>Rodado Díaz</nombre>
	  <set number="1">15</set>
	  <set number="2">15</set>
	  <set number="3">0</set>
	</equipo>
	<equipo>
	  <nombre>González Moreno</nombre>
	  <set number="1">10</set>
	  <set number="2">10</set>
	  <set number="3">0</set>
	</equipo>
  </partido>
  <partido>
	<fecha>5 AGO</fecha>
	<hora>20:00</hora>
	<categoria>FEM</categoria>
	<grupo>C</grupo>
	<fase>LIGA</fase>
	<equipo>
	  <nombre>Zipi Y Zape</nombre>
	  <set number="1">6</set>
	  <set number="2">4</set>
	  <set number="3">0</set>
	</equipo>
	<equipo>
	  <nombre>Leti Y Diana</nombre>
	  <set number="1">15</set>
	  <set number="2">15</set>
	  <set number="3">0</set>
	</equipo>
  </partido>
  <partido>
	<fecha>5 AGO</fecha>
	<hora>21:00</hora>
	<categoria>FEM</categoria>
	<grupo>C</grupo>
	<fase>LIGA</fase>
	<equipo>
	  <nombre>Ana Y Marta</nombre>
	  <set number="1">7</set>
	  <set number="2">10</set>
	  <set number="3">0</set>
	</equipo>
	<equipo>
	  <nombre>Leti Y Diana</nombre>
	  <set number="1">15</set>
	  <set number="2">15</set>
	  <set number="3">0</set>
	</equipo>
  </partido>
  <partido>
	<fecha>5 AGO</fecha>
	<hora>22:00</hora>
	<categoria>FEM</categoria>
	<grupo>C</grupo>
	<fase>LIGA</fase>
	<equipo>
	  <nombre>Ana Y Marta</nombre>
	  <set number="1">15</set>
	  <set number="2">12</set>
	  <set number="3">11</set>
	</equipo>
	<equipo>
	  <nombre>Zipi Y Zape</nombre>
	  <set number="1">8</set>
	  <set number="2">15</set>
	  <set number="3">9</set>
	</equipo>
  </partido>
  <partido>
	<fecha>5 AGO</fecha>
	<hora>22:30</hora>
	<categoria>MIX</categoria>
	<grupo>E</grupo>
	<fase>LIGA</fase>
	<equipo>
	  <nombre>Astilleros Rojas</nombre>
	  <set number="1">17</set>
	  <set number="2">15</set>
	  <set number="3">0</set>
	</equipo>
	<equipo>
	  <nombre>Cortés Rodado</nombre>
	  <set number="1">15</set>
	  <set number="2">11</set>
	  <set number="3">0</set>
	</equipo>
  </partido>
  <partido>
	<fecha>5 AGO</fecha>
	<hora>23:30</hora>
	<categoria>MIX</categoria>
	<grupo>C</grupo>
	<fase>LIGA</fase>
	<equipo>
	  <nombre>Nieto Díaz</nombre>
	  <set number="1">15</set>
	  <set number="2">15</set>
	  <set number="3">0</set>
	</equipo>
	<equipo>
	  <nombre>Arévalo Mora</nombre>
	  <set number="1">7</set>
	  <set number="2">11</set>
	  <set number="3">0</set>
	</equipo>
  </partido>
  <partido>
	<fecha>5 AGO</fecha>
	<hora>00:00</hora>
	<categoria>MIX</categoria>
	<grupo>E</grupo>
	<fase>LIGA</fase>
	<equipo>
	  <nombre>Astilleros Rojas</nombre>
	  <set number="1">15</set>
	  <set number="2">15</set>
	  <set number="3">0</set>
	</equipo>
	<equipo>
	  <nombre>González Peco</nombre>
	  <set number="1">7</set>
	  <set number="2">12</set>
	  <set number="3">0</set>
	</equipo>
  </partido>
  <partido>
	<fecha>5 AGO</fecha>
	<hora>00:30</hora>
	<categoria>MIX</categoria>
	<grupo>C</grupo>
	<fase>LIGA</fase>
	<equipo>
	  <nombre>Arévalo Mora</nombre>
	  <set number="1">15</set>
	  <set number="2">15</set>
	  <set number="3">0</set>
	</equipo>
	<equipo>
	  <nombre>Cortés García</nombre>
	  <set number="1">11</set>
	  <set number="2">5</set>
	  <set number="3">0</set>
	</equipo>
  </partido>
  <partido>
	<fecha>6 AGO</fecha>
	<hora>19:00</hora>
	<categoria>AFI</categoria>
	<grupo>-</grupo>
	<fase>LIGA</fase>
	<equipo>
	  <nombre>Guti Y Yeste</nombre>
	  <set number="1">15</set>
	  <set number="2">15</set>
	  <set number="3">0</set>
	</equipo>
	<equipo>
	  <nombre>Agapito Y Juanfri</nombre>
	  <set number="1">6</set>
	  <set number="2">5</set>
	  <set number="3">0</set>
	</equipo>
  </partido>
  <partido>
	<fecha>6 AGO</fecha>
	<hora>19:30</hora>
	<categoria>AFI</categoria>
	<grupo>-</grupo>
	<fase>LIGA</fase>
	<equipo>
	  <nombre>Jungle Fever</nombre>
	  <set number="1">10</set>
	  <set number="2">7</set>
	  <set number="3">0</set>
	</equipo>
	<equipo>
	  <nombre>Hermanos Martín</nombre>
	  <set number="1">15</set>
	  <set number="2">15</set>
	  <set number="3">0</set>
	</equipo>
  </partido>
  <partido>
	<fecha>6 AGO</fecha>
	<hora>20:00</hora>
	<categoria>AFI</categoria>
	<grupo>-</grupo>
	<fase>LIGA</fase>
	<equipo>
	  <nombre>Jumping Crew</nombre>
	  <set number="1">4</set>
	  <set number="2">6</set>
	  <set number="3">0</set>
	</equipo>
	<equipo>
	  <nombre>Rafa Y Óscar</nombre>
	  <set number="1">15</set>
	  <set number="2">15</set>
	  <set number="3">0</set>
	</equipo>
  </partido>
  <partido>
	<fecha>6 AGO</fecha>
	<hora>20:30</hora>
	<categoria>AFI</categoria>
	<grupo>-</grupo>
	<fase>LIGA</fase>
	<equipo>
	  <nombre>Mandril Y Comadreja</nombre>
	  <set number="1">7</set>
	  <set number="2">12</set>
	  <set number="3">0</set>
	</equipo>
	<equipo>
	  <nombre>The Cousins</nombre>
	  <set number="1">15</set>
	  <set number="2">15</set>
	  <set number="3">0</set>
	</equipo>
  </partido>
  <partido>
	<fecha>6 AGO</fecha>
	<hora>21:00</hora>
	<categoria>AFI</categoria>
	<grupo>-</grupo>
	<fase>LIGA</fase>
	<equipo>
	  <nombre>El Rolón Volador</nombre>
	  <set number="1">15</set>
	  <set number="2">15</set>
	  <set number="3">0</set>
	</equipo>
	<equipo>
	  <nombre>Ruano Y Rodrigo</nombre>
	  <set number="1">6</set>
	  <set number="2">11</set>
	  <set number="3">0</set>
	</equipo>
  </partido>
  <partido>
	<fecha>6 AGO</fecha>
	<hora>21:30</hora>
	<categoria>AFI</categoria>
	<grupo>-</grupo>
	<fase>LIGA</fase>
	<equipo>
	  <nombre>Rojas Casas</nombre>
	  <set number="1">15</set>
	  <set number="2">5</set>
	  <set number="3">8</set>
	</equipo>
	<equipo>
	  <nombre>Los Del Rodeo</nombre>
	  <set number="1">13</set>
	  <set number="2">15</set>
	  <set number="3">11</set>
	</equipo>
  </partido>
  <partido>
	<fecha>6 AGO</fecha>
	<hora>22:00</hora>
	<categoria>MIX</categoria>
	<grupo>B</grupo>
	<fase>LIGA</fase>
	<equipo>
	  <nombre>Hervás Maján</nombre>
	  <set number="1">15</set>
	  <set number="2">15</set>
	  <set number="3">0</set>
	</equipo>
	<equipo>
	  <nombre>Martín García</nombre>
	  <set number="1">10</set>
	  <set number="2">6</set>
	  <set number="3">0</set>
	</equipo>
  </partido>
  <partido>
	<fecha>6 AGO</fecha>
	<hora>22:30</hora>
	<categoria>MAS</categoria>
	<grupo>D</grupo>
	<fase>LIGA</fase>
	<equipo>
	  <nombre>Hervás Maján</nombre>
	  <set number="1">15</set>
	  <set number="2">15</set>
	  <set number="3">0</set>
	</equipo>
	<equipo>
	  <nombre>Fer Y Sergi</nombre>
	  <set number="1">10</set>
	  <set number="2">12</set>
	  <set number="3">0</set>
	</equipo>
  </partido>
  <partido>
	<fecha>6 AGO</fecha>
	<hora>23:00</hora>
	<categoria>AFI</categoria>
	<grupo>-</grupo>
	<fase>LIGA</fase>
	<equipo>
	  <nombre>Vicsa Electricidad</nombre>
	  <set number="1">11</set>
	  <set number="2">15</set>
	  <set number="3">9</set>
	</equipo>
	<equipo>
	  <nombre>Morcillo De La Cruz</nombre>
	  <set number="1">15</set>
	  <set number="2">13</set>
	  <set number="3">11</set>
	</equipo>
  </partido>
  <partido>
	<fecha>6 AGO</fecha>
	<hora>23:30</hora>
	<categoria>MAS</categoria>
	<grupo>D</grupo>
	<fase>LIGA</fase>
	<equipo>
	  <nombre>Hervás Maján</nombre>
	  <set number="1">15</set>
	  <set number="2">11</set>
	  <set number="3">0</set>
	</equipo>
	<equipo>
	  <nombre>Arévalo Toribio</nombre>
	  <set number="1">11</set>
	  <set number="2">10</set>
	  <set number="3">0</set>
	</equipo>
  </partido>
  <partido>
	<fecha>6 AGO</fecha>
	<hora>00:00</hora>
	<categoria>AFI</categoria>
	<grupo>-</grupo>
	<fase>LIGA</fase>
	<equipo>
	  <nombre>Bastante Gómez</nombre>
	  <set number="1">15</set>
	  <set number="2">12</set>
	  <set number="3">11</set>
	</equipo>
	<equipo>
	  <nombre>Illescas Punzón</nombre>
	  <set number="1">9</set>
	  <set number="2">15</set>
	  <set number="3">9</set>
	</equipo>
  </partido>
  <partido>
	<fecha>6 AGO</fecha>
	<hora>00:30</hora>
	<categoria>MAS</categoria>
	<grupo>D</grupo>
	<fase>LIGA</fase>
	<equipo>
	  <nombre>Arévalo Toribio</nombre>
	  <set number="1">10</set>
	  <set number="2">10</set>
	  <set number="3">0</set>
	</equipo>
	<equipo>
	  <nombre>Fer Y Sergi</nombre>
	  <set number="1">15</set>
	  <set number="2">15</set>
	  <set number="3">0</set>
	</equipo>
  </partido>
  <partido>
	<fecha>6 AGO</fecha>
	<hora>01:00</hora>
	<categoria>MIX</categoria>
	<grupo>F</grupo>
	<fase>LIGA</fase>
	<equipo>
	  <nombre>Cortés Rodado</nombre>
	  <set number="1">0</set>
	  <set number="2">0</set>
	  <set number="3">0</set>
	</equipo>
	<equipo>
	  <nombre>González Peco</nombre>
	  <set number="1">0</set>
	  <set number="2">0</set>
	  <set number="3">0</set>
	</equipo>
  </partido>
  <partido>
	<fecha>7 AGO</fecha>
	<hora>19:00</hora>
	<categoria>FEM</categoria>
	<grupo>C</grupo>
	<fase>LIGA</fase>
	<equipo>
	  <nombre>Seni Y Juni</nombre>
	  <set number="1">10</set>
	  <set number="2">15</set>
	  <set number="3">11</set>
	</equipo>
	<equipo>
	  <nombre>Zipi Y Zape</nombre>
	  <set number="1">15</set>
	  <set number="2">9</set>
	  <set number="3">8</set>
	</equipo>
  </partido>
  <partido>
	<fecha>7 AGO</fecha>
	<hora>19:30</hora>
	<categoria>AFI</categoria>
	<grupo>-</grupo>
	<fase>LIGA</fase>
	<equipo>
	  <nombre>Hermanos Martín</nombre>
	  <set number="1">15</set>
	  <set number="2">15</set>
	  <set number="3">0</set>
	</equipo>
	<equipo>
	  <nombre>El Rolón Volador</nombre>
	  <set number="1">9</set>
	  <set number="2">13</set>
	  <set number="3">0</set>
	</equipo>
  </partido>
  <partido>
	<fecha>7 AGO</fecha>
	<hora>20:00</hora>
	<categoria>AFI</categoria>
	<grupo>-</grupo>
	<fase>LIGA</fase>
	<equipo>
	  <nombre>The Cousins</nombre>
	  <set number="1">9</set>
	  <set number="2">15</set>
	  <set number="3">11</set>
	</equipo>
	<equipo>
	  <nombre>Bastante Gómez</nombre>
	  <set number="1">15</set>
	  <set number="2">12</set>
	  <set number="3">4</set>
	</equipo>
  </partido>
  <partido>
	<fecha>7 AGO</fecha>
	<hora>20:30</hora>
	<categoria>FEM</categoria>
	<grupo>C</grupo>
	<fase>LIGA</fase>
	<equipo>
	  <nombre>Seni Y Juni</nombre>
	  <set number="1">15</set>
	  <set number="2">16</set>
	  <set number="3">11</set>
	</equipo>
	<equipo>
	  <nombre>Leti Y Diana</nombre>
	  <set number="1">9</set>
	  <set number="2">18</set>
	  <set number="3">5</set>
	</equipo>
  </partido>
  <partido>
	<fecha>7 AGO</fecha>
	<hora>21:00</hora>
	<categoria>AFI</categoria>
	<grupo>-</grupo>
	<fase>LIGA</fase>
	<equipo>
	  <nombre>Los Del Rodeo</nombre>
	  <set number="1">15</set>
	  <set number="2">14</set>
	  <set number="3">0</set>
	</equipo>
	<equipo>
	  <nombre>Morcillo De La Cruz</nombre>
	  <set number="1">17</set>
	  <set number="2">16</set>
	  <set number="3">0</set>
	</equipo>
  </partido>
  <partido>
	<fecha>7 AGO</fecha>
	<hora>21:30</hora>
	<categoria>AFI</categoria>
	<grupo>-</grupo>
	<fase>LIGA</fase>
	<equipo>
	  <nombre>Rafa Y Óscar</nombre>
	  <set number="1">6</set>
	  <set number="2">12</set>
	  <set number="3">0</set>
	</equipo>
	<equipo>
	  <nombre>Guti Y Yeste</nombre>
	  <set number="1">15</set>
	  <set number="2">15</set>
	  <set number="3">0</set>
	</equipo>
  </partido>
  <partido>
	<fecha>7 AGO</fecha>
	<hora>22:00</hora>
	<categoria>MAS</categoria>
	<grupo>D</grupo>
	<fase>LIGA</fase>
	<equipo>
	  <nombre>Hervás Maján</nombre>
	  <set number="1">15</set>
	  <set number="2">15</set>
	  <set number="3">0</set>
	</equipo>
	<equipo>
	  <nombre>Anoelin Y Guzmalín</nombre>
	  <set number="1">11</set>
	  <set number="2">11</set>
	  <set number="3">0</set>
	</equipo>
  </partido>
  <partido>
	<fecha>7 AGO</fecha>
	<hora>22:30</hora>
	<categoria>MIX</categoria>
	<grupo>B</grupo>
	<fase>LIGA</fase>
	<equipo>
	  <nombre>Hervás Maján</nombre>
	  <set number="1">14</set>
	  <set number="2">15</set>
	  <set number="3">11</set>
	</equipo>
	<equipo>
	  <nombre>Pozo Gil</nombre>
	  <set number="1">16</set>
	  <set number="2">13</set>
	  <set number="3">8</set>
	</equipo>
  </partido>
  <partido>
	<fecha>7 AGO</fecha>
	<hora>23:00</hora>
	<categoria>AFI</categoria>
	<grupo>-</grupo>
	<fase>LIGA</fase>
	<equipo>
	  <nombre>The Cousins</nombre>
	  <set number="1">9</set>
	  <set number="2">15</set>
	  <set number="3">11</set>
	</equipo>
	<equipo>
	  <nombre>Morcillo De La Cruz </nombre>
	  <set number="1">15</set>
	  <set number="2">11</set>
	  <set number="3">6</set>
	</equipo>
  </partido>
  <partido>
	<fecha>7 AGO</fecha>
	<hora>23:30</hora>
	<categoria>AFI</categoria>
	<grupo>-</grupo>
	<fase>LIGA</fase>
	<equipo>
	  <nombre>Guti Y Yeste</nombre>
	  <set number="1">15</set>
	  <set number="2">15</set>
	  <set number="3">0</set>
	</equipo>
	<equipo>
	  <nombre>Hermanos Martín </nombre>
	  <set number="1">9</set>
	  <set number="2">11</set>
	  <set number="3">0</set>
	</equipo>
  </partido>
  <partido>
	<fecha>7 AGO</fecha>
	<hora>00:00</hora>
	<categoria>MIX</categoria>
	<grupo>B</grupo>
	<fase>LIGA</fase>
	<equipo>
	  <nombre>Pozo Gil</nombre>
	  <set number="1">15</set>
	  <set number="2">15</set>
	  <set number="3">0</set>
	</equipo>
	<equipo>
	  <nombre>Martín García</nombre>
	  <set number="1">4</set>
	  <set number="2">5</set>
	  <set number="3">0</set>
	</equipo>
  </partido>
  <partido>
	<fecha>7 AGO</fecha>
	<hora>00:30</hora>
	<categoria>AFI</categoria>
	<grupo>-</grupo>
	<fase>LIGA</fase>
	<equipo>
	  <nombre>Hermanos Martín</nombre>
	  <set number="1">8</set>
	  <set number="2">7</set>
	  <set number="3">0</set>
	</equipo>
	<equipo>
	  <nombre>Morcillo De La Cruz</nombre>
	  <set number="1">15</set>
	  <set number="2">15</set>
	  <set number="3">0</set>
	</equipo>
  </partido>
  <partido>
	<fecha>6 AGO</fecha>
	<hora>11:00</hora>
	<categoria>FEM</categoria>
	<grupo>B</grupo>
	<fase>LIGA</fase>
	<equipo>
	  <nombre>Rojas Sánchez</nombre>
	  <set number="1">9</set>
	  <set number="2">15</set>
	  <set number="3">9</set>
	</equipo>
	<equipo>
	  <nombre>Mora Peco</nombre>
	  <set number="1">15</set>
	  <set number="2">10</set>
	  <set number="3">11</set>
	</equipo>
  </partido>
  <partido>
	<fecha>8 AGO</fecha>
	<hora>18:00</hora>
	<categoria>MIX</categoria>
	<grupo>D</grupo>
	<fase>LIGA</fase>
	<equipo>
	  <nombre>Moronta Pérez</nombre>
	  <set number="1">15</set>
	  <set number="2">15</set>
	  <set number="3">0</set>
	</equipo>
	<equipo>
	  <nombre>León Escobar</nombre>
	  <set number="1">5</set>
	  <set number="2">5</set>
	  <set number="3">0</set>
	</equipo>
  </partido>
  <partido>
	<fecha>8 AGO</fecha>
	<hora>18:30</hora>
	<categoria>MIX</categoria>
	<grupo>A</grupo>
	<fase>LIGA</fase>
	<equipo>
	  <nombre>Moronta Dorado</nombre>
	  <set number="1">15</set>
	  <set number="2">15</set>
	  <set number="3">0</set>
	</equipo>
	<equipo>
	  <nombre>Hervás Loro</nombre>
	  <set number="1">4</set>
	  <set number="2">6</set>
	  <set number="3">0</set>
	</equipo>
  </partido>
  <partido>
	<fecha>8 AGO</fecha>
	<hora>19:00</hora>
	<categoria>MAS</categoria>
	<grupo>C</grupo>
	<fase>LIGA</fase>
	<equipo>
	  <nombre>Mora Einbergs</nombre>
	  <set number="1">15</set>
	  <set number="2">15</set>
	  <set number="3">0</set>
	</equipo>
	<equipo>
	  <nombre>Sánchez Parreño</nombre>
	  <set number="1">7</set>
	  <set number="2">13</set>
	  <set number="3">0</set>
	</equipo>
  </partido>
  <partido>
	<fecha>8 AGO</fecha>
	<hora>19:30</hora>
	<categoria>MAS</categoria>
	<grupo>B</grupo>
	<fase>LIGA</fase>
	<equipo>
	  <nombre>Moronta Moronta</nombre>
	  <set number="1">15</set>
	  <set number="2">15</set>
	  <set number="3">0</set>
	</equipo>
	<equipo>
	  <nombre>González Moreno</nombre>
	  <set number="1">12</set>
	  <set number="2">10</set>
	  <set number="3">0</set>
	</equipo>
  </partido>
  <partido>
	<fecha>8 AGO</fecha>
	<hora>20:00</hora>
	<categoria>FEM</categoria>
	<grupo>A</grupo>
	<fase>LIGA</fase>
	<equipo>
	  <nombre>Dorado Muñoz</nombre>
	  <set number="1">15</set>
	  <set number="2">15</set>
	  <set number="3">0</set>
	</equipo>
	<equipo>
	  <nombre>Alba Y Ángela</nombre>
	  <set number="1">9</set>
	  <set number="2">8</set>
	  <set number="3">0</set>
	</equipo>
  </partido>
  <partido>
	<fecha>8 AGO</fecha>
	<hora>20:30</hora>
	<categoria>FEM</categoria>
	<grupo>B</grupo>
	<fase>LIGA</fase>
	<equipo>
	  <nombre>Rojas Sánchez</nombre>
	  <set number="1">15</set>
	  <set number="2">15</set>
	  <set number="3">0</set>
	</equipo>
	<equipo>
	  <nombre>Martínez Martínez</nombre>
	  <set number="1">8</set>
	  <set number="2">6</set>
	  <set number="3">0</set>
	</equipo>
  </partido>
  <partido>
	<fecha>8 AGO</fecha>
	<hora>21:00</hora>
	<categoria>FEM</categoria>
	<grupo>C</grupo>
	<fase>LIGA</fase>
	<equipo>
	  <nombre>Ana Y Marta</nombre>
	  <set number="1">11</set>
	  <set number="2">16</set>
	  <set number="3">8</set>
	</equipo>
	<equipo>
	  <nombre>Seni Y Juni</nombre>
	  <set number="1">15</set>
	  <set number="2">14</set>
	  <set number="3">11</set>
	</equipo>
  </partido>
  <partido>
	<fecha>8 AGO</fecha>
	<hora>21:30</hora>
	<categoria>FEM</categoria>
	<grupo>A</grupo>
	<fase>LIGA</fase>
	<equipo>
	  <nombre>No Sin Mi Cerveza</nombre>
	  <set number="1">15</set>
	  <set number="2">15</set>
	  <set number="3">0</set>
	</equipo>
	<equipo>
	  <nombre>Chusi Y Carol</nombre>
	  <set number="1">10</set>
	  <set number="2">5</set>
	  <set number="3">0</set>
	</equipo>
  </partido>
  <partido>
	<fecha>8 AGO</fecha>
	<hora>22:00</hora>
	<categoria>MIX</categoria>
	<grupo>F</grupo>
	<fase>LIGA</fase>
	<equipo>
	  <nombre>Martínez Mora</nombre>
	  <set number="1">15</set>
	  <set number="2">15</set>
	  <set number="3">0</set>
	</equipo>
	<equipo>
	  <nombre>Borrás Martínez</nombre>
	  <set number="1">7</set>
	  <set number="2">8</set>
	  <set number="3">0</set>
	</equipo>
  </partido>
  <partido>
	<fecha>8 AGO</fecha>
	<hora>22:30</hora>
	<categoria>MAS</categoria>
	<grupo>B</grupo>
	<fase>LIGA</fase>
	<equipo>
	  <nombre>Cano Rick</nombre>
	  <set number="1">6</set>
	  <set number="2">11</set>
	  <set number="3">0</set>
	</equipo>
	<equipo>
	  <nombre>Moronta Moronta</nombre>
	  <set number="1">15</set>
	  <set number="2">15</set>
	  <set number="3">0</set>
	</equipo>
  </partido>
  <partido>
	<fecha>8 AGO</fecha>
	<hora>23:00</hora>
	<categoria>MAS</categoria>
	<grupo>A</grupo>
	<fase>LIGA</fase>
	<equipo>
	  <nombre>Los Pelaos</nombre>
	  <set number="1">10</set>
	  <set number="2">15</set>
	  <set number="3">6</set>
	</equipo>
	<equipo>
	  <nombre>Brillo Valadés</nombre>
	  <set number="1">15</set>
	  <set number="2">11</set>
	  <set number="3">11</set>
	</equipo>
  </partido>
  <partido>
	<fecha>8 AGO</fecha>
	<hora>23:30</hora>
	<categoria>MAS</categoria>
	<grupo>C</grupo>
	<fase>LIGA</fase>
	<equipo>
	  <nombre>Mora Einbergs</nombre>
	  <set number="1">15</set>
	  <set number="2">15</set>
	  <set number="3">0</set>
	</equipo>
	<equipo>
	  <nombre>Beldad Pozo</nombre>
	  <set number="1">13</set>
	  <set number="2">12</set>
	  <set number="3">0</set>
	</equipo>
  </partido>
  <partido>
	<fecha>8 AGO</fecha>
	<hora>00:00</hora>
	<categoria>MIX</categoria>
	<grupo>D</grupo>
	<fase>LIGA</fase>
	<equipo>
	  <nombre>Muñoz Brillo</nombre>
	  <set number="1">15</set>
	  <set number="2">15</set>
	  <set number="3">0</set>
	</equipo>
	<equipo>
	  <nombre>Cano Martín</nombre>
	  <set number="1">5</set>
	  <set number="2">9</set>
	  <set number="3">0</set>
	</equipo>
  </partido>
  <partido>
	<fecha>8 AGO</fecha>
	<hora>00:30</hora>
	<categoria>MAS</categoria>
	<grupo>A</grupo>
	<fase>LIGA</fase>
	<equipo>
	  <nombre>Los Pelaos</nombre>
	  <set number="1">11</set>
	  <set number="2">9</set>
	  <set number="3">0</set>
	</equipo>
	<equipo>
	  <nombre>Laboratorios Sys</nombre>
	  <set number="1">15</set>
	  <set number="2">15</set>
	  <set number="3">0</set>
	</equipo>
  </partido>
  <partido>
	<fecha>8 AGO</fecha>
	<hora>01:00</hora>
	<categoria>MIX</categoria>
	<grupo>F</grupo>
	<fase>LIGA</fase>
	<equipo>
	  <nombre>Borrás Martínez</nombre>
	  <set number="1">8</set>
	  <set number="2">16</set>
	  <set number="3">0</set>
	</equipo>
	<equipo>
	  <nombre>A Kinito No Nos Gana Nadie</nombre>
	  <set number="1">15</set>
	  <set number="2">15</set>
	  <set number="3">0</set>
	</equipo>
  </partido>
  <partido>
	<fecha>8 AGO</fecha>
	<hora>01:30</hora>
	<categoria>MAS</categoria>
	<grupo>B</grupo>
	<fase>LIGA</fase>
	<equipo>
	  <nombre>Cano Rick</nombre>
	  <set number="1">15</set>
	  <set number="2">15</set>
	  <set number="3">0</set>
	</equipo>
	<equipo>
	  <nombre>González Moreno</nombre>
	  <set number="1">13</set>
	  <set number="2">11</set>
	  <set number="3">0</set>
	</equipo>
  </partido>
  <partido>
	<fecha>8 AGO</fecha>
	<hora>02:00</hora>
	<categoria>MAS</categoria>
	<grupo>A</grupo>
	<fase>LIGA</fase>
	<equipo>
	  <nombre>Brillo Valadés</nombre>
	  <set number="1">15</set>
	  <set number="2">15</set>
	  <set number="3">0</set>
	</equipo>
	<equipo>
	  <nombre>Ferre López</nombre>
	  <set number="1">11</set>
	  <set number="2">7</set>
	  <set number="3">0</set>
	</equipo>
  </partido>
  <partido>
	<fecha>7 AGO</fecha>
	<hora>01:00</hora>
	<categoria>MIX</categoria>
	<grupo>E</grupo>
	<fase>LIGA</fase>
	<equipo>
	  <nombre>Cortés Rodado</nombre>
	  <set number="1">17</set>
	  <set number="2">15</set>
	  <set number="3">0</set>
	</equipo>
	<equipo>
	  <nombre>González Peco</nombre>
	  <set number="1">15</set>
	  <set number="2">6</set>
	  <set number="3">0</set>
	</equipo>
  </partido>
  <partido>
	<fecha>9 AGO</fecha>
	<hora>09:00</hora>
	<categoria>MIX</categoria>
	<grupo>B</grupo>
	<fase>LIGA</fase>
	<equipo>
	  <nombre>Hervás Maján</nombre>
	  <set number="1">15</set>
	  <set number="2">15</set>
	  <set number="3">0</set>
	</equipo>
	<equipo>
	  <nombre>Madavilla</nombre>
	  <set number="1">8</set>
	  <set number="2">11</set>
	  <set number="3">0</set>
	</equipo>
  </partido>
  <partido>
	<fecha>9 AGO</fecha>
	<hora>09:30</hora>
	<categoria>FEM</categoria>
	<grupo>D</grupo>
	<fase>LIGA</fase>
	<equipo>
	  <nombre>Gómez Cortés</nombre>
	  <set number="1">15</set>
	  <set number="2">15</set>
	  <set number="3">0</set>
	</equipo>
	<equipo>
	  <nombre>García Sánchez</nombre>
	  <set number="1">12</set>
	  <set number="2">6</set>
	  <set number="3">0</set>
	</equipo>
  </partido>
  <partido>
	<fecha>9 AGO</fecha>
	<hora>10:00</hora>
	<categoria>FEM</categoria>
	<grupo>B</grupo>
	<fase>LIGA</fase>
	<equipo>
	  <nombre>Martínez Martínez</nombre>
	  <set number="1">15</set>
	  <set number="2">15</set>
	  <set number="3">0</set>
	</equipo>
	<equipo>
	  <nombre>El Retorno De Antonia</nombre>
	  <set number="1">0</set>
	  <set number="2">0</set>
	  <set number="3">0</set>
	</equipo>
  </partido>
  <partido>
	<fecha>9 AGO</fecha>
	<hora>10:30</hora>
	<categoria>FEM</categoria>
	<grupo>D</grupo>
	<fase>LIGA</fase>
	<equipo>
	  <nombre>García Sánchez</nombre>
	  <set number="1">6</set>
	  <set number="2">13</set>
	  <set number="3">0</set>
	</equipo>
	<equipo>
	  <nombre>Toletum</nombre>
	  <set number="1">15</set>
	  <set number="2">15</set>
	  <set number="3">0</set>
	</equipo>
  </partido>
  <partido>
	<fecha>9 AGO</fecha>
	<hora>11:00</hora>
	<categoria>FEM</categoria>
	<grupo>A</grupo>
	<fase>LIGA</fase>
	<equipo>
	  <nombre>Dorado Muñoz</nombre>
	  <set number="1">15</set>
	  <set number="2">15</set>
	  <set number="3">0</set>
	</equipo>
	<equipo>
	  <nombre>Chusi Y Carol</nombre>
	  <set number="1">6</set>
	  <set number="2">7</set>
	  <set number="3">0</set>
	</equipo>
  </partido>
  <partido>
	<fecha>9 AGO</fecha>
	<hora>11:30</hora>
	<categoria>MAS</categoria>
	<grupo>B</grupo>
	<fase>LIGA</fase>
	<equipo>
	  <nombre>Rodado Díaz</nombre>
	  <set number="1">15</set>
	  <set number="2">15</set>
	  <set number="3">0</set>
	</equipo>
	<equipo>
	  <nombre>Cano Rick</nombre>
	  <set number="1">13</set>
	  <set number="2">11</set>
	  <set number="3">0</set>
	</equipo>
  </partido>
  <partido>
	<fecha>9 AGO</fecha>
	<hora>12:00</hora>
	<categoria>MAS</categoria>
	<grupo>A</grupo>
	<fase>LIGA</fase>
	<equipo>
	  <nombre>Laboratorios Sys</nombre>
	  <set number="1">15</set>
	  <set number="2">15</set>
	  <set number="3">0</set>
	</equipo>
	<equipo>
	  <nombre>Ferre López</nombre>
	  <set number="1">8</set>
	  <set number="2">11</set>
	  <set number="3">0</set>
	</equipo>
  </partido>
  <partido>
	<fecha>9 AGO</fecha>
	<hora>12:30</hora>
	<categoria>MAS</categoria>
	<grupo>C</grupo>
	<fase>LIGA</fase>
	<equipo>
	  <nombre>Mora Einbergs</nombre>
	  <set number="1">15</set>
	  <set number="2">15</set>
	  <set number="3">0</set>
	</equipo>
	<equipo>
	  <nombre>Nieto Brígido</nombre>
	  <set number="1">10</set>
	  <set number="2">7</set>
	  <set number="3">0</set>
	</equipo>
  </partido>
  <partido>
	<fecha>9 AGO</fecha>
	<hora>13:00</hora>
	<categoria>MAS</categoria>
	<grupo>B</grupo>
	<fase>LIGA</fase>
	<equipo>
	  <nombre>Rodado Díaz</nombre>
	  <set number="1">8</set>
	  <set number="2">9</set>
	  <set number="3">0</set>
	</equipo>
	<equipo>
	  <nombre>Moronta Moronta</nombre>
	  <set number="1">15</set>
	  <set number="2">15</set>
	  <set number="3">0</set>
	</equipo>
  </partido>
  <partido>
	<fecha>9 AGO</fecha>
	<hora>13:30</hora>
	<categoria>MAS</categoria>
	<grupo>A</grupo>
	<fase>LIGA</fase>
	<equipo>
	  <nombre>Laboratorios Sys</nombre>
	  <set number="1">15</set>
	  <set number="2">15</set>
	  <set number="3">0</set>
	</equipo>
	<equipo>
	  <nombre>Brillo Valadés</nombre>
	  <set number="1">7</set>
	  <set number="2">7</set>
	  <set number="3">0</set>
	</equipo>
  </partido>
  <partido>
	<fecha>9 AGO</fecha>
	<hora>16:00</hora>
	<categoria>MIX</categoria>
	<grupo>F</grupo>
	<fase>LIGA</fase>
	<equipo>
	  <nombre>Ferre Carretero</nombre>
	  <set number="1">12</set>
	  <set number="2">14</set>
	  <set number="3">0</set>
	</equipo>
	<equipo>
	  <nombre>Martínez Mora</nombre>
	  <set number="1">15</set>
	  <set number="2">16</set>
	  <set number="3">0</set>
	</equipo>
  </partido>
  <partido>
	<fecha>9 AGO</fecha>
	<hora>16:30</hora>
	<categoria>MIX</categoria>
	<grupo>B</grupo>
	<fase>LIGA</fase>
	<equipo>
	  <nombre>Madavilla</nombre>
	  <set number="1">17</set>
	  <set number="2">15</set>
	  <set number="3">0</set>
	</equipo>
	<equipo>
	  <nombre>Martín García</nombre>
	  <set number="1">15</set>
	  <set number="2">8</set>
	  <set number="3">0</set>
	</equipo>
  </partido>
  <partido>
	<fecha>9 AGO</fecha>
	<hora>17:00</hora>
	<categoria>MIX</categoria>
	<grupo>A</grupo>
	<fase>LIGA</fase>
	<equipo>
	  <nombre>Anónimos</nombre>
	  <set number="1">15</set>
	  <set number="2">17</set>
	  <set number="3">0</set>
	</equipo>
	<equipo>
	  <nombre>Carretero Monroy</nombre>
	  <set number="1">10</set>
	  <set number="2">15</set>
	  <set number="3">0</set>
	</equipo>
  </partido>
  <partido>
	<fecha>9 AGO</fecha>
	<hora>17:30</hora>
	<categoria>MIX</categoria>
	<grupo>F</grupo>
	<fase>LIGA</fase>
	<equipo>
	  <nombre>Ferre Carretero</nombre>
	  <set number="1">12</set>
	  <set number="2">6</set>
	  <set number="3">0</set>
	</equipo>
	<equipo>
	  <nombre>A Kinito No Nos Gana Nadie</nombre>
	  <set number="1">15</set>
	  <set number="2">15</set>
	  <set number="3">0</set>
	</equipo>
  </partido>
  <partido>
	<fecha>9 AGO</fecha>
	<hora>18:00</hora>
	<categoria>MIX</categoria>
	<grupo>D</grupo>
	<fase>LIGA</fase>
	<equipo>
	  <nombre>Moronta Pérez</nombre>
	  <set number="1">15</set>
	  <set number="2">15</set>
	  <set number="3">0</set>
	</equipo>
	<equipo>
	  <nombre>Cano Martín</nombre>
	  <set number="1">7</set>
	  <set number="2">9</set>
	  <set number="3">0</set>
	</equipo>
  </partido>
  <partido>
	<fecha>9 AGO</fecha>
	<hora>18:30</hora>
	<categoria>MIX</categoria>
	<grupo>A</grupo>
	<fase>LIGA</fase>
	<equipo>
	  <nombre>Moronta Dorado</nombre>
	  <set number="1">15</set>
	  <set number="2">15</set>
	  <set number="3">0</set>
	</equipo>
	<equipo>
	  <nombre>Carretero Monroy</nombre>
	  <set number="1">11</set>
	  <set number="2">5</set>
	  <set number="3">0</set>
	</equipo>
  </partido>
  <partido>
	<fecha>9 AGO</fecha>
	<hora>19:00</hora>
	<categoria>MIX</categoria>
	<grupo>F</grupo>
	<fase>LIGA</fase>
	<equipo>
	  <nombre>Ferre Carretero</nombre>
	  <set number="1">15</set>
	  <set number="2">15</set>
	  <set number="3">0</set>
	</equipo>
	<equipo>
	  <nombre>Borrás Martínez</nombre>
	  <set number="1">8</set>
	  <set number="2">10</set>
	  <set number="3">0</set>
	</equipo>
  </partido>
  <partido>
	<fecha>9 AGO</fecha>
	<hora>19:30</hora>
	<categoria>MIX</categoria>
	<grupo>D</grupo>
	<fase>LIGA</fase>
	<equipo>
	  <nombre>Moronta Pérez</nombre>
	  <set number="1">15</set>
	  <set number="2">13</set>
	  <set number="3">11</set>
	</equipo>
	<equipo>
	  <nombre>Muñoz Brillo</nombre>
	  <set number="1">5</set>
	  <set number="2">15</set>
	  <set number="3">0</set>
	</equipo>
  </partido>
  <partido>
	<fecha>9 AGO</fecha>
	<hora>20:00</hora>
	<categoria>MIX</categoria>
	<grupo>F</grupo>
	<fase>LIGA</fase>
	<equipo>
	  <nombre>Martínez Mora</nombre>
	  <set number="1">12</set>
	  <set number="2">12</set>
	  <set number="3">0</set>
	</equipo>
	<equipo>
	  <nombre>A Kinito No Nos Gana Nadie</nombre>
	  <set number="1">15</set>
	  <set number="2">15</set>
	  <set number="3">0</set>
	</equipo>
  </partido>
  <partido>
	<fecha>9 AGO</fecha>
	<hora>20:30</hora>
	<categoria>MIX</categoria>
	<grupo>A</grupo>
	<fase>LIGA</fase>
	<equipo>
	  <nombre>Moronta Dorado</nombre>
	  <set number="1">16</set>
	  <set number="2">15</set>
	  <set number="3">0</set>
	</equipo>
	<equipo>
	  <nombre>Anónimos</nombre>
	  <set number="1">14</set>
	  <set number="2">4</set>
	  <set number="3">0</set>
	</equipo>
  </partido>
  <partido>
	<fecha>9 AGO</fecha>
	<hora>21:00</hora>
	<categoria>MIX</categoria>
	<grupo>B</grupo>
	<fase>LIGA</fase>
	<equipo>
	  <nombre>Madavilla</nombre>
	  <set number="1">15</set>
	  <set number="2">15</set>
	  <set number="3">0</set>
	</equipo>
	<equipo>
	  <nombre>Pozo Gil</nombre>
	  <set number="1">10</set>
	  <set number="2">12</set>
	  <set number="3">0</set>
	</equipo>
  </partido>
  <partido>
	<fecha>9 AGO</fecha>
	<hora>21:30</hora>
	<categoria>MAS</categoria>
	<grupo>A</grupo>
	<fase>LIGA</fase>
	<equipo>
	  <nombre>Los Pelaos</nombre>
	  <set number="1">9</set>
	  <set number="2">10</set>
	  <set number="3">0</set>
	</equipo>
	<equipo>
	  <nombre>Ferre López</nombre>
	  <set number="1">15</set>
	  <set number="2">15</set>
	  <set number="3">0</set>
	</equipo>
  </partido>
  <partido>
	<fecha>9 AGO</fecha>
	<hora>22:00</hora>
	<categoria>FEM</categoria>
	<grupo>A</grupo>
	<fase>LIGA</fase>
	<equipo>
	  <nombre>Alba Y Ángela</nombre>
	  <set number="1">6</set>
	  <set number="2">7</set>
	  <set number="3">0</set>
	</equipo>
	<equipo>
	  <nombre>No Sin Mi Cerveza</nombre>
	  <set number="1">15</set>
	  <set number="2">15</set>
	  <set number="3">0</set>
	</equipo>
  </partido>
  <partido>
	<fecha>9 AGO</fecha>
	<hora>22:30</hora>
	<categoria>FEM</categoria>
	<grupo>D</grupo>
	<fase>LIGA</fase>
	<equipo>
	  <nombre>Gómez Cortés</nombre>
	  <set number="1">15</set>
	  <set number="2">8</set>
	  <set number="3">5</set>
	</equipo>
	<equipo>
	  <nombre>Toletum</nombre>
	  <set number="1">12</set>
	  <set number="2">15</set>
	  <set number="3">11</set>
	</equipo>
  </partido>
  <partido>
	<fecha>9 AGO</fecha>
	<hora>23:00</hora>
	<categoria>FEM</categoria>
	<grupo>B</grupo>
	<fase>LIGA</fase>
	<equipo>
	  <nombre>Martínez Martínez</nombre>
	  <set number="1">15</set>
	  <set number="2">12</set>
	  <set number="3">7</set>
	</equipo>
	<equipo>
	  <nombre>Mora Peco</nombre>
	  <set number="1">12</set>
	  <set number="2">15</set>
	  <set number="3">11</set>
	</equipo>
  </partido>
  <partido>
	<fecha>9 AGO</fecha>
	<hora>23:30</hora>
	<categoria>FEM</categoria>
	<grupo>A</grupo>
	<fase>LIGA</fase>
	<equipo>
	  <nombre>Dorado Muñoz</nombre>
	  <set number="1">15</set>
	  <set number="2">15</set>
	  <set number="3">0</set>
	</equipo>
	<equipo>
	  <nombre>No Sin Mi Cerveza</nombre>
	  <set number="1">7</set>
	  <set number="2">11</set>
	  <set number="3">0</set>
	</equipo>
  </partido>
  <partido>
	<fecha>9 AGO</fecha>
	<hora>00:00</hora>
	<categoria>FEM</categoria>
	<grupo>A</grupo>
	<fase>LIGA</fase>
	<equipo>
	  <nombre>Alba Y Ángela</nombre>
	  <set number="1">15</set>
	  <set number="2">15</set>
	  <set number="3">0</set>
	</equipo>
	<equipo>
	  <nombre>Chusi Y Carol</nombre>
	  <set number="1">12</set>
	  <set number="2">9</set>
	  <set number="3">0</set>
	</equipo>
  </partido>
  <partido>
	<fecha>9 AGO</fecha>
	<hora>00:30</hora>
	<categoria>MAS</categoria>
	<grupo>-</grupo>
	<fase>LIGA</fase>
	<equipo>
	  <nombre>Beldad Pozo</nombre>
	  <set number="1">16</set>
	  <set number="2">12</set>
	  <set number="3">8</set>
	</equipo>
	<equipo>
	  <nombre>Moronta Moronta</nombre>
	  <set number="1">14</set>
	  <set number="2">15</set>
	  <set number="3">11</set>
	</equipo>
  </partido>
  <partido>
	<fecha>9 AGO</fecha>
	<hora>01:00</hora>
	<categoria>MAS</categoria>
	<grupo>-</grupo>
	<fase>LIGA</fase>
	<equipo>
	  <nombre>Hervás Maján</nombre>
	  <set number="1">15</set>
	  <set number="2">16</set>
	  <set number="3">0</set>
	</equipo>
	<equipo>
	  <nombre>Brillo Valadés</nombre>
	  <set number="1">9</set>
	  <set number="2">14</set>
	  <set number="3">0</set>
	</equipo>
  </partido>
  <partido>
	<fecha>9 AGO</fecha>
	<hora>01:30</hora>
	<categoria>FEM</categoria>
	<grupo>-</grupo>
	<fase>LIGA</fase>
	<equipo>
	  <nombre>Toletum</nombre>
	  <set number="1">9</set>
	  <set number="2">3</set>
	  <set number="3">0</set>
	</equipo>
	<equipo>
	  <nombre>No Sin Mi Cerveza</nombre>
	  <set number="1">15</set>
	  <set number="2">15</set>
	  <set number="3">0</set>
	</equipo>
  </partido>
  <partido>
	<fecha>9 AGO</fecha>
	<hora>02:00</hora>
	<categoria>FEM</categoria>
	<grupo>-</grupo>
	<fase>LIGA</fase>
	<equipo>
	  <nombre>Gómez Cortés</nombre>
	  <set number="1">8</set>
	  <set number="2">7</set>
	  <set number="3">0</set>
	</equipo>
	<equipo>
	  <nombre>Dorado Muñoz</nombre>
	  <set number="1">15</set>
	  <set number="2">15</set>
	  <set number="3">0</set>
	</equipo>
  </partido>
  <partido>
	<fecha>9 AGO</fecha>
	<hora>16:30</hora>
	<categoria>MIX</categoria>
	<grupo>D</grupo>
	<fase>LIGA</fase>
	<equipo>
	  <nombre>Cano Martín</nombre>
	  <set number="1">15</set>
	  <set number="2">15</set>
	  <set number="3">0</set>
	</equipo>
	<equipo>
	  <nombre>León Escobar</nombre>
	  <set number="1">13</set>
	  <set number="2">8</set>
	  <set number="3">0</set>
	</equipo>
  </partido>
  <partido>
	<fecha>10 AGO</fecha>
	<hora>09:30</hora>
	<categoria>MIX</categoria>
	<grupo>A</grupo>
	<fase>LIGA</fase>
	<equipo>
	  <nombre>Anónimos</nombre>
	  <set number="1">15</set>
	  <set number="2">15</set>
	  <set number="3">0</set>
	</equipo>
	<equipo>
	  <nombre>Hervás Loro</nombre>
	  <set number="1">12</set>
	  <set number="2">12</set>
	  <set number="3">0</set>
	</equipo>
  </partido>
  <partido>
	<fecha>10 AGO</fecha>
	<hora>10:00</hora>
	<categoria>MIX</categoria>
	<grupo>D</grupo>
	<fase>LIGA</fase>
	<equipo>
	  <nombre>Muñoz Brillo</nombre>
	  <set number="1">15</set>
	  <set number="2">15</set>
	  <set number="3">0</set>
	</equipo>
	<equipo>
	  <nombre>León Escobar</nombre>
	  <set number="1">7</set>
	  <set number="2">13</set>
	  <set number="3">0</set>
	</equipo>
  </partido>
  <partido>
	<fecha>10 AGO</fecha>
	<hora>10:30</hora>
	<categoria>FEM</categoria>
	<grupo>-</grupo>
	<fase>LIGA</fase>
	<equipo>
	  <nombre>Seni Y Juni</nombre>
	  <set number="1">7</set>
	  <set number="2">7</set>
	  <set number="3">0</set>
	</equipo>
	<equipo>
	  <nombre>Rojas Sánchez</nombre>
	  <set number="1">15</set>
	  <set number="2">15</set>
	  <set number="3">0</set>
	</equipo>
  </partido>
  <partido>
	<fecha>10 AGO</fecha>
	<hora>11:00</hora>
	<categoria>FEM</categoria>
	<grupo>-</grupo>
	<fase>LIGA</fase>
	<equipo>
	  <nombre>Leti Y Diana</nombre>
	  <set number="1">15</set>
	  <set number="2">15</set>
	  <set number="3">0</set>
	</equipo>
	<equipo>
	  <nombre>Mora Peco</nombre>
	  <set number="1">13</set>
	  <set number="2">11</set>
	  <set number="3">0</set>
	</equipo>
  </partido>
  <partido>
	<fecha>10 AGO</fecha>
	<hora>11:30</hora>
	<categoria>MAS</categoria>
	<grupo>-</grupo>
	<fase>LIGA</fase>
	<equipo>
	  <nombre>Fer Y Sergi</nombre>
	  <set number="1">8</set>
	  <set number="2">9</set>
	  <set number="3">0</set>
	</equipo>
	<equipo>
	  <nombre>Laboratorios SyS</nombre>
	  <set number="1">15</set>
	  <set number="2">15</set>
	  <set number="3">0</set>
	</equipo>
  </partido>
  <partido>
	<fecha>10 AGO</fecha>
	<hora>12:00</hora>
	<categoria>MAS</categoria>
	<grupo>-</grupo>
	<fase>LIGA</fase>
	<equipo>
	  <nombre>Mora Einbergs</nombre>
	  <set number="1">15</set>
	  <set number="2">15</set>
	  <set number="3">0</set>
	</equipo>
	<equipo>
	  <nombre>Rodado Diaz</nombre>
	  <set number="1">11</set>
	  <set number="2">11</set>
	  <set number="3">0</set>
	</equipo>
  </partido>
  <partido>
	<fecha>10 AGO</fecha>
	<hora>12:30</hora>
	<categoria>MIX</categoria>
	<grupo>-</grupo>
	<fase>LIGA</fase>
	<equipo>
	  <nombre>Hervás Maján</nombre>
	  <set number="1">16</set>
	  <set number="2">15</set>
	  <set number="3">0</set>
	</equipo>
	<equipo>
	  <nombre>Díaz Nieto</nombre>
	  <set number="1">14</set>
	  <set number="2">7</set>
	  <set number="3">0</set>
	</equipo>
  </partido>
  <partido>
	<fecha>10 AGO</fecha>
	<hora>13:00</hora>
	<categoria>MIX</categoria>
	<grupo>-</grupo>
	<fase>LIGA</fase>
	<equipo>
	  <nombre>A Kinito No Nos Gana Nadie</nombre>
	  <set number="1">12</set>
	  <set number="2">15</set>
	  <set number="3">5</set>
	</equipo>
	<equipo>
	  <nombre>Astilleros Rojas</nombre>
	  <set number="1">15</set>
	  <set number="2">6</set>
	  <set number="3">11</set>
	</equipo>
  </partido>
  <partido>
	<fecha>10 AGO</fecha>
	<hora>13:30</hora>
	<categoria>MIX</categoria>
	<grupo>-</grupo>
	<fase>LIGA</fase>
	<equipo>
	  <nombre>Toribio Cañizares</nombre>
	  <set number="1">7</set>
	  <set number="2">7</set>
	  <set number="3">0</set>
	</equipo>
	<equipo>
	  <nombre>Moronta Pérez</nombre>
	  <set number="1">15</set>
	  <set number="2">15</set>
	  <set number="3">0</set>
	</equipo>
  </partido>
  <partido>
	<fecha>10 AGO</fecha>
	<hora>16:00</hora>
	<categoria>MIX</categoria>
	<grupo>-</grupo>
	<fase>LIGA</fase>
	<equipo>
	  <nombre>Muñoz Brillo</nombre>
	  <set number="1">15</set>
	  <set number="2">4</set>
	  <set number="3">4</set>
	</equipo>
	<equipo>
	  <nombre>Moronta Dorado</nombre>
	  <set number="1">9</set>
	  <set number="2">15</set>
	  <set number="3">11</set>
	</equipo>
  </partido>
  <partido>
	<fecha>10 AGO</fecha>
	<hora>16:30</hora>
	<categoria>FEM</categoria>
	<grupo>-</grupo>
	<fase>LIGA</fase>
	<equipo>
	  <nombre>Rojas Sánchez</nombre>
	  <set number="1">9</set>
	  <set number="2">8</set>
	  <set number="3">0</set>
	</equipo>
	<equipo>
	  <nombre>No Sin Mi Cerveza </nombre>
	  <set number="1">15</set>
	  <set number="2">15</set>
	  <set number="3">0</set>
	</equipo>
  </partido>
  <partido>
	<fecha>10 AGO</fecha>
	<hora>17:00</hora>
	<categoria>FEM</categoria>
	<grupo>-</grupo>
	<fase>LIGA</fase>
	<equipo>
	  <nombre>Leti Y Diana</nombre>
	  <set number="1">10</set>
	  <set number="2">8</set>
	  <set number="3">0</set>
	</equipo>
	<equipo>
	  <nombre>Dorado Muñoz </nombre>
	  <set number="1">15</set>
	  <set number="2">15</set>
	  <set number="3">0</set>
	</equipo>
  </partido>
  <partido>
	<fecha>10 AGO</fecha>
	<hora>17:30</hora>
	<categoria>MIX</categoria>
	<grupo>-</grupo>
	<fase>LIGA</fase>
	<equipo>
	  <nombre>Hervás Maján</nombre>
	  <set number="1">15</set>
	  <set number="2">15</set>
	  <set number="3">0</set>
	</equipo>
	<equipo>
	  <nombre>Astilleros Rojas </nombre>
	  <set number="1">9</set>
	  <set number="2">8</set>
	  <set number="3">0</set>
	</equipo>
  </partido>
  <partido>
	<fecha>10 AGO</fecha>
	<hora>18:00</hora>
	<categoria>MIX</categoria>
	<grupo>-</grupo>
	<fase>LIGA</fase>
	<equipo>
	  <nombre>Moronta Pérez</nombre>
	  <set number="1">9</set>
	  <set number="2">15</set>
	  <set number="3">8</set>
	</equipo>
	<equipo>
	  <nombre> Moronta Dorado</nombre>
	  <set number="1">15</set>
	  <set number="2">11</set>
	  <set number="3">11</set>
	</equipo>
  </partido>
  <partido>
	<fecha>10 AGO</fecha>
	<hora>19:00</hora>
	<categoria>MAS</categoria>
	<grupo>-</grupo>
	<fase>LIGA</fase>
	<equipo>
	  <nombre>Hervás Maján</nombre>
	  <set number="1">7</set>
	  <set number="2">12</set>
	  <set number="3">0</set>
	</equipo>
	<equipo>
	  <nombre> Mora Einbergs</nombre>
	  <set number="1">15</set>
	  <set number="2">15</set>
	  <set number="3">0</set>
	</equipo>
  </partido>
  <partido>
	<fecha>10 AGO</fecha>
	<hora>19:30</hora>
	<categoria>MAS</categoria>
	<grupo>-</grupo>
	<fase>LIGA</fase>
	<equipo>
	  <nombre>Moronta Moronta</nombre>
	  <set number="1">11</set>
	  <set number="2">15</set>
	  <set number="3">3</set>
	</equipo>
	<equipo>
	  <nombre> Laboratorios SyS</nombre>
	  <set number="1">15</set>
	  <set number="2">12</set>
	  <set number="3">11</set>
	</equipo>
  </partido>
  <partido>
	<fecha>10 AGO</fecha>
	<hora>20:00</hora>
	<categoria>FEM</categoria>
	<grupo>-</grupo>
	<fase>LIGA</fase>
	<equipo>
	  <nombre>Rojas Sánchez</nombre>
	  <set number="1">15</set>
	  <set number="2">15</set>
	  <set number="3">0</set>
	</equipo>
	<equipo>
	  <nombre>Leti Y Diana</nombre>
	  <set number="1">7</set>
	  <set number="2">8</set>
	  <set number="3">0</set>
	</equipo>
  </partido>
  <partido>
	<fecha>10 AGO</fecha>
	<hora>20:30</hora>
	<categoria>MIX</categoria>
	<grupo>-</grupo>
	<fase>LIGA</fase>
	<equipo>
	  <nombre>Hervás Maján</nombre>
	  <set number="1">12</set>
	  <set number="2">8</set>
	  <set number="3">0</set>
	</equipo>
	<equipo>
	  <nombre>Moronta Pérez</nombre>
	  <set number="1">15</set>
	  <set number="2">15</set>
	  <set number="3">0</set>
	</equipo>
  </partido>
  <partido>
	<fecha>10 AGO</fecha>
	<hora>21:00</hora>
	<categoria>MAS</categoria>
	<grupo>-</grupo>
	<fase>LIGA</fase>
	<equipo>
	  <nombre>Moronta Moronta</nombre>
	  <set number="1">15</set>
	  <set number="2">15</set>
	  <set number="3">0</set>
	</equipo>
	<equipo>
	  <nombre>Hervás Maján</nombre>
	  <set number="1">0</set>
	  <set number="2">0</set>
	  <set number="3">0</set>
	</equipo>
  </partido>
  <partido>
	<fecha>10 AGO</fecha>
	<hora>21:30</hora>
	<categoria>AFI</categoria>
	<grupo>-</grupo>
	<fase>LIGA</fase>
	<equipo>
	  <nombre>Guti y Yeste</nombre>
	  <set number="1">18</set>
	  <set number="2">15</set>
	  <set number="3">0</set>
	</equipo>
	<equipo>
	  <nombre>The Cousins</nombre>
	  <set number="1">16</set>
	  <set number="2">12</set>
	  <set number="3">0</set>
	</equipo>
  </partido>
  <partido>
	<fecha>10 AGO</fecha>
	<hora>22:00</hora>
	<categoria>MIX</categoria>
	<grupo>-</grupo>
	<fase>LIGA</fase>
	<equipo>
	  <nombre>Astilleros Rojas</nombre>
	  <set number="1">7</set>
	  <set number="2">10</set>
	  <set number="3">0</set>
	</equipo>
	<equipo>
	  <nombre> Moronta Dorado</nombre>
	  <set number="1">15</set>
	  <set number="2">15</set>
	  <set number="3">0</set>
	</equipo>
  </partido>
  <partido>
	<fecha>10 AGO</fecha>
	<hora>22:30</hora>
	<categoria>FEM</categoria>
	<grupo>-</grupo>
	<fase>LIGA</fase>
	<equipo>
	  <nombre>No Sin Mi Cerveza</nombre>
	  <set number="1">12</set>
	  <set number="2">15</set>
	  <set number="3">0</set>
	</equipo>
	<equipo>
	  <nombre> Dorado Muñoz</nombre>
	  <set number="1">15</set>
	  <set number="2">17</set>
	  <set number="3">0</set>
	</equipo>
  </partido>
  <partido>
	<fecha>10 AGO</fecha>
	<hora>23:00</hora>
	<categoria>MAS</categoria>
	<grupo>-</grupo>
	<fase>LIGA</fase>
	<equipo>
	  <nombre>Mora Einbergs</nombre>
	  <set number="1">9</set>
	  <set number="2">8</set>
	  <set number="3">0</set>
	</equipo>
	<equipo>
	  <nombre>Laboratorios SyS </nombre>
	  <set number="1">15</set>
	  <set number="2">15</set>
	  <set number="3">0</set>
	</equipo>
  </partido>
</torneo>
